{
	"date": "2022-11-14",
	"repo": {
		"name": "github.com/wallabag/wallabag",
		"commit": "1124632f8ab6e59b31bf91a16cd8104ed04a50f6"
	},
	"scorecard": {
		"version": "v4.8.0-62-g439f90a",
		"commit": "439f90ac7d46379c876401d748feea4553a796c9"
	},
	"score": 7.5,
	"checks": [{
		"name": "Code-Review",
		"score": 10,
		"reason": "15 out of last 15 changesets reviewed before merge -- score normalized to 10",
		"details": null,
		"documentation": {
			"short": "Determines if the project requires code review before pull requests (aka merge requests) are merged.",
			"url": "https://github.com/ossf/scorecard/blob/439f90ac7d46379c876401d748feea4553a796c9/docs/checks.md#code-review"
		}
	}, {
		"name": "Maintained",
		"score": 10,
		"reason": "30 commit(s) out of 30 and 17 issue activity out of 30 found in the last 90 days -- score normalized to 10",
		"details": null,
		"documentation": {
			"short": "Determines if the project is \"actively maintained\".",
			"url": "https://github.com/ossf/scorecard/blob/439f90ac7d46379c876401d748feea4553a796c9/docs/checks.md#maintained"
		}
	}, {
		"name": "CII-Best-Practices",
		"reason": "no badge detected",
		"details": null,
		"documentation": {
			"short": "Determines if the project has an OpenSSF (formerly CII) Best Practices Badge.",
			"url": "https://github.com/ossf/scorecard/blob/439f90ac7d46379c876401d748feea4553a796c9/docs/checks.md#cii-best-practices"
		}
	}, {
		"name": "Vulnerabilities",
		"score": 10,
		"reason": "no vulnerabilities detected",
		"details": null,
		"documentation": {
			"short": "Determines if the project has open, known unfixed vulnerabilities.",
			"url": "https://github.com/ossf/scorecard/blob/439f90ac7d46379c876401d748feea4553a796c9/docs/checks.md#vulnerabilities"
		}
	}, {
		"name": "Signed-Releases",
		"reason": "0 out of 5 artifacts are signed or have provenance",
		"details": ["Warn: release artifact 2.5.2 does not have provenance: https://api.github.com/repos/wallabag/wallabag/releases/80595526", "Warn: release artifact 2.5.2 not signed: https://api.github.com/repos/wallabag/wallabag/releases/80595526", "Warn: release artifact 2.5.1 does not have provenance: https://api.github.com/repos/wallabag/wallabag/releases/69028563", "Warn: release artifact 2.5.1 not signed: https://api.github.com/repos/wallabag/wallabag/releases/69028563", "Warn: release artifact 2.5.0 does not have provenance: https://api.github.com/repos/wallabag/wallabag/releases/67461231", "Warn: release artifact 2.5.0 not signed: https://api.github.com/repos/wallabag/wallabag/releases/67461231", "Warn: release artifact 2.4.3 does not have provenance: https://api.github.com/repos/wallabag/wallabag/releases/59524726", "Warn: release artifact 2.4.3 not signed: https://api.github.com/repos/wallabag/wallabag/releases/59524726", "Warn: release artifact 2.4.2 does not have provenance: https://api.github.com/repos/wallabag/wallabag/releases/39870484", "Warn: release artifact 2.4.2 not signed: https://api.github.com/repos/wallabag/wallabag/releases/39870484"],
		"documentation": {
			"short": "Determines if the project cryptographically signs release artifacts.",
			"url": "https://github.com/ossf/scorecard/blob/439f90ac7d46379c876401d748feea4553a796c9/docs/checks.md#signed-releases"
		}
	}, {
		"name": "Token-Permissions",
		"score": 10,
		"reason": "tokens are read-only in GitHub workflows",
		"details": null,
		"documentation": {
			"short": "Determines if the project's workflows follow the principle of least privilege.",
			"url": "https://github.com/ossf/scorecard/blob/439f90ac7d46379c876401d748feea4553a796c9/docs/checks.md#token-permissions"
		}
	}, {
		"name": "Security-Policy",
		"score": 9,
		"reason": "security policy file detected",
		"details": ["Info: Found linked content in security policy: SECURITY.md", "Info: Found text in security policy: SECURITY.md", "Warn: One or no descriptive hints of disclosure, vulnerability, and/or timelines in security policy: SECURITY.md", "Info: security policy detected in current repo: SECURITY.md"],
		"documentation": {
			"short": "Determines if the project has published a security policy.",
			"url": "https://github.com/ossf/scorecard/blob/439f90ac7d46379c876401d748feea4553a796c9/docs/checks.md#security-policy"
		}
	}, {
		"name": "License",
		"score": 10,
		"reason": "license file detected",
		"details": ["Info: : COPYING.md:1"],
		"documentation": {
			"short": "Determines if the project has defined a license.",
			"url": "https://github.com/ossf/scorecard/blob/439f90ac7d46379c876401d748feea4553a796c9/docs/checks.md#license"
		}
	}, {
		"name": "Dangerous-Workflow",
		"score": 10,
		"reason": "no dangerous workflow patterns detected",
		"details": null,
		"documentation": {
			"short": "Determines if the project's GitHub Action workflows avoid dangerous patterns.",
			"url": "https://github.com/ossf/scorecard/blob/439f90ac7d46379c876401d748feea4553a796c9/docs/checks.md#dangerous-workflow"
		}
	}, {
		"name": "Packaging",
		"score": -1,
		"reason": "no published package detected",
		"details": ["Warn: no GitHub publishing workflow detected"],
		"documentation": {
			"short": "Determines if the project is published as a package that others can easily download, install, easily update, and uninstall.",
			"url": "https://github.com/ossf/scorecard/blob/439f90ac7d46379c876401d748feea4553a796c9/docs/checks.md#packaging"
		}
	}, {
		"name": "Binary-Artifacts",
		"score": 10,
		"reason": "no binaries found in the repo",
		"details": null,
		"documentation": {
			"short": "Determines if the project has generated executable (binary) artifacts in the source repository.",
			"url": "https://github.com/ossf/scorecard/blob/439f90ac7d46379c876401d748feea4553a796c9/docs/checks.md#binary-artifacts"
		}
	}, {
		"name": "Pinned-Dependencies",
		"score": 7,
		"reason": "dependency not pinned by hash detected -- score normalized to 7",
		"details": ["Warn: containerImage not pinned by hash: docker/php/Dockerfile:1: pin your Docker image by updating php:7.4-fpm to php:7.4-fpm@sha256:3ac7c8c74b2b047c7cb273469d74fc0d59b857aa44043e6ea6a0084372811d5b", "Warn: containerImage not pinned by hash: docker/php/Dockerfile:84", "Warn: npmCommand not pinned by hash: docker/php/Dockerfile:63", "Info: GitHub-owned GitHubActions are pinned", "Info: Third-party GitHubActions are pinned", "Info: no insecure (not pinned by hash) dependency downloads found in Dockerfiles", "Info: no insecure (not pinned by hash) dependency downloads found in shell scripts"],
		"documentation": {
			"short": "Determines if the project has declared and pinned the dependencies of its build process.",
			"url": "https://github.com/ossf/scorecard/blob/439f90ac7d46379c876401d748feea4553a796c9/docs/checks.md#pinned-dependencies"
		}
	}, {
		"name": "Dependency-Update-Tool",
		"score": 10,
		"reason": "update tool detected",
		"details": ["Info: Dependabot detected"],
		"documentation": {
			"short": "Determines if the project uses a dependency update tool.",
			"url": "https://github.com/ossf/scorecard/blob/439f90ac7d46379c876401d748feea4553a796c9/docs/checks.md#dependency-update-tool"
		}
	}, {
		"name": "SAST",
		"reason": "SAST tool is not run on all commits -- score normalized to 0",
		"details": ["Warn: 0 commits out of 30 are checked with a SAST tool", "Warn: CodeQL tool not detected"],
		"documentation": {
			"short": "Determines if the project uses static code analysis.",
			"url": "https://github.com/ossf/scorecard/blob/439f90ac7d46379c876401d748feea4553a796c9/docs/checks.md#sast"
		}
	}, {
		"name": "Fuzzing",
		"reason": "project is not fuzzed",
		"details": null,
		"documentation": {
			"short": "Determines if the project uses fuzzing.",
			"url": "https://github.com/ossf/scorecard/blob/439f90ac7d46379c876401d748feea4553a796c9/docs/checks.md#fuzzing"
		}
	}, {
		"name": "Branch-Protection",
		"score": 8,
		"reason": "branch protection is not maximal on development and all release branches",
		"details": ["Info: 'force pushes' disabled on branch 'master'", "Info: 'allow deletion' disabled on branch 'master'", "Info: status check found to merge onto on branch 'master'", "Warn: number of required reviewers is only 1 on branch 'master'", "Warn: codeowner review is not required on branch 'master'"],
		"documentation": {
			"short": "Determines if the default and release branches are protected with GitHub's branch protection settings.",
			"url": "https://github.com/ossf/scorecard/blob/439f90ac7d46379c876401d748feea4553a796c9/docs/checks.md#branch-protection"
		}
	}]
}