{
    "files": [],
    "packages": [
      {
        "name": "org.assertj.assertj-core",
        "SPDXID": "SPDXRef-Package-0F126D72864910ABE25F0A871B04597782185F8AB802C3AB9580F4FB8A550CB5",
        "downloadLocation": "NOASSERTION",
        "filesAnalyzed": false,
        "licenseConcluded": "NOASSERTION",
        "licenseInfoFromFiles": [
          "NOASSERTION"
        ],
        "licenseDeclared": "NOASSERTION",
        "copyrightText": "NOASSERTION",
        "versionInfo": "3.13.2",
        "externalRefs": [
          {
            "referenceCategory": "PACKAGE-MANAGER",
            "referenceType": "purl",
            "referenceLocator": "pkg:maven/org.assertj/assertj-core@3.13.2"
          }
        ],
        "supplier": "NOASSERTION"
      },
      {
        "name": "org.junit.jupiter.junit-jupiter",
        "SPDXID": "SPDXRef-Package-E5EAD97FB2A2318163EE05FA2622DBC7676D40631520E94F276C1576999F7364",
        "downloadLocation": "NOASSERTION",
        "filesAnalyzed": false,
        "licenseConcluded": "NOASSERTION",
        "licenseInfoFromFiles": [
          "NOASSERTION"
        ],
        "licenseDeclared": "NOASSERTION",
        "copyrightText": "NOASSERTION",
        "versionInfo": "5.5.2",
        "externalRefs": [
          {
            "referenceCategory": "PACKAGE-MANAGER",
            "referenceType": "purl",
            "referenceLocator": "pkg:maven/org.junit.jupiter/junit-jupiter@5.5.2"
          }
        ],
        "supplier": "NOASSERTION"
      },
      {
        "name": "org.springframework.spring-jcl",
        "SPDXID": "SPDXRef-Package-6BA79E403F10E4FF19D0C4CB2C0CAFA2286576C9CA9A034316A51B250B320615",
        "downloadLocation": "NOASSERTION",
        "filesAnalyzed": false,
        "licenseConcluded": "NOASSERTION",
        "licenseInfoFromFiles": [
          "NOASSERTION"
        ],
        "licenseDeclared": "NOASSERTION",
        "copyrightText": "NOASSERTION",
        "versionInfo": "5.2.3.RELEASE",
        "externalRefs": [
          {
            "referenceCategory": "PACKAGE-MANAGER",
            "referenceType": "purl",
            "referenceLocator": "pkg:maven/org.springframework/spring-jcl@5.2.3.RELEASE"
          }
        ],
        "supplier": "NOASSERTION"
      },
      {
        "name": "org.bouncycastle.bcprov-jdk18on",
        "SPDXID": "SPDXRef-Package-4CD6BEF9A21ECD30039D25C5DEF23A397FADE5780C77CA826CEDF184C85349BE",
        "downloadLocation": "NOASSERTION",
        "filesAnalyzed": false,
        "licenseConcluded": "NOASSERTION",
        "licenseInfoFromFiles": [
          "NOASSERTION"
        ],
        "licenseDeclared": "NOASSERTION",
        "copyrightText": "NOASSERTION",
        "versionInfo": "1.71",
        "externalRefs": [
          {
            "referenceCategory": "PACKAGE-MANAGER",
            "referenceType": "purl",
            "referenceLocator": "pkg:maven/org.bouncycastle/bcprov-jdk18on@1.71"
          }
        ],
        "supplier": "NOASSERTION"
      },
      {
        "name": "net.bytebuddy.byte-buddy-agent",
        "SPDXID": "SPDXRef-Package-CE2645995E7C5D35374354BB83B4EC929C6FF4F5E8879940AE82DFCB85A25E06",
        "downloadLocation": "NOASSERTION",
        "filesAnalyzed": false,
        "licenseConcluded": "NOASSERTION",
        "licenseInfoFromFiles": [
          "NOASSERTION"
        ],
        "licenseDeclared": "NOASSERTION",
        "copyrightText": "NOASSERTION",
        "versionInfo": "1.10.6",
        "externalRefs": [
          {
            "referenceCategory": "PACKAGE-MANAGER",
            "referenceType": "purl",
            "referenceLocator": "pkg:maven/net.bytebuddy/byte-buddy-agent@1.10.6"
          }
        ],
        "supplier": "NOASSERTION"
      },
      {
        "name": "ch.qos.logback.logback-classic",
        "SPDXID": "SPDXRef-Package-34570F7131A006073C0E15AB766CD5A79255D6DE2A0EDEF69D9B9DADABDEC1A8",
        "downloadLocation": "NOASSERTION",
        "filesAnalyzed": false,
        "licenseConcluded": "NOASSERTION",
        "licenseInfoFromFiles": [
          "NOASSERTION"
        ],
        "licenseDeclared": "NOASSERTION",
        "copyrightText": "NOASSERTION",
        "versionInfo": "1.2.3",
        "externalRefs": [
          {
            "referenceCategory": "PACKAGE-MANAGER",
            "referenceType": "purl",
            "referenceLocator": "pkg:maven/ch.qos.logback/logback-classic@1.2.3"
          }
        ],
        "supplier": "NOASSERTION"
      },
      {
        "name": "org.ow2.asm.asm",
        "SPDXID": "SPDXRef-Package-87901215DA3F8AD2F8ED55D8DAFCC24E14227D5098FD1E7CC6B833C8BBAF3E3F",
        "downloadLocation": "NOASSERTION",
        "filesAnalyzed": false,
        "licenseConcluded": "NOASSERTION",
        "licenseInfoFromFiles": [
          "NOASSERTION"
        ],
        "licenseDeclared": "NOASSERTION",
        "copyrightText": "NOASSERTION",
        "versionInfo": "5.0.4",
        "externalRefs": [
          {
            "referenceCategory": "PACKAGE-MANAGER",
            "referenceType": "purl",
            "referenceLocator": "pkg:maven/org.ow2.asm/asm@5.0.4"
          }
        ],
        "supplier": "NOASSERTION"
      },
      {
        "name": "org.junit.platform.junit-platform-engine",
        "SPDXID": "SPDXRef-Package-64C75A94B9FCF2899ACD501FA1AE605994B8915213C05F9A7633FCB7AAC6DDDC",
        "downloadLocation": "NOASSERTION",
        "filesAnalyzed": false,
        "licenseConcluded": "NOASSERTION",
        "licenseInfoFromFiles": [
          "NOASSERTION"
        ],
        "licenseDeclared": "NOASSERTION",
        "copyrightText": "NOASSERTION",
        "versionInfo": "1.5.2",
        "externalRefs": [
          {
            "referenceCategory": "PACKAGE-MANAGER",
            "referenceType": "purl",
            "referenceLocator": "pkg:maven/org.junit.platform/junit-platform-engine@1.5.2"
          }
        ],
        "supplier": "NOASSERTION"
      },
      {
        "name": "org.apache.logging.log4j.log4j-api",
        "SPDXID": "SPDXRef-Package-71B92262C7455B6A4AB5733D7985F52D83DAEFDD6AB2C12AB0D4BDFEC92D7FC2",
        "downloadLocation": "NOASSERTION",
        "filesAnalyzed": false,
        "licenseConcluded": "NOASSERTION",
        "licenseInfoFromFiles": [
          "NOASSERTION"
        ],
        "licenseDeclared": "NOASSERTION",
        "copyrightText": "NOASSERTION",
        "versionInfo": "2.12.1",
        "externalRefs": [
          {
            "referenceCategory": "PACKAGE-MANAGER",
            "referenceType": "purl",
            "referenceLocator": "pkg:maven/org.apache.logging.log4j/log4j-api@2.12.1"
          }
        ],
        "supplier": "NOASSERTION"
      },
      {
        "name": "org.springframework.boot.spring-boot-test",
        "SPDXID": "SPDXRef-Package-AF61F230B02D2ADDB9CE830578142294C95805C33902ABAD4E77FD6CEA2813AA",
        "downloadLocation": "NOASSERTION",
        "filesAnalyzed": false,
        "licenseConcluded": "NOASSERTION",
        "licenseInfoFromFiles": [
          "NOASSERTION"
        ],
        "licenseDeclared": "NOASSERTION",
        "copyrightText": "NOASSERTION",
        "versionInfo": "2.2.4.RELEASE",
        "externalRefs": [
          {
            "referenceCategory": "PACKAGE-MANAGER",
            "referenceType": "purl",
            "referenceLocator": "pkg:maven/org.springframework.boot/spring-boot-test@2.2.4.RELEASE"
          }
        ],
        "supplier": "NOASSERTION"
      },
      {
        "name": "org.springframework.spring-core",
        "SPDXID": "SPDXRef-Package-7CEC26E8F875C5306D34A7D6455348CC7BF504AEE3FA259B6C16D9F2239BCE1A",
        "downloadLocation": "NOASSERTION",
        "filesAnalyzed": false,
        "licenseConcluded": "NOASSERTION",
        "licenseInfoFromFiles": [
          "NOASSERTION"
        ],
        "licenseDeclared": "NOASSERTION",
        "copyrightText": "NOASSERTION",
        "versionInfo": "5.2.3.RELEASE",
        "externalRefs": [
          {
            "referenceCategory": "PACKAGE-MANAGER",
            "referenceType": "purl",
            "referenceLocator": "pkg:maven/org.springframework/spring-core@5.2.3.RELEASE"
          }
        ],
        "supplier": "NOASSERTION"
      },
      {
        "name": "net.bytebuddy.byte-buddy",
        "SPDXID": "SPDXRef-Package-5B6C31B74437D07CE6B95C02E958898842139D0E60921BA2F5EEC228FA367AE2",
        "downloadLocation": "NOASSERTION",
        "filesAnalyzed": false,
        "licenseConcluded": "NOASSERTION",
        "licenseInfoFromFiles": [
          "NOASSERTION"
        ],
        "licenseDeclared": "NOASSERTION",
        "copyrightText": "NOASSERTION",
        "versionInfo": "1.10.6",
        "externalRefs": [
          {
            "referenceCategory": "PACKAGE-MANAGER",
            "referenceType": "purl",
            "referenceLocator": "pkg:maven/net.bytebuddy/byte-buddy@1.10.6"
          }
        ],
        "supplier": "NOASSERTION"
      },
      {
        "name": "org.junit.platform.junit-platform-commons",
        "SPDXID": "SPDXRef-Package-D688F8F3C0920FC253AB04DA89676A6EAABDF19EFAA12C1F88D484B18F0C6C4A",
        "downloadLocation": "NOASSERTION",
        "filesAnalyzed": false,
        "licenseConcluded": "NOASSERTION",
        "licenseInfoFromFiles": [
          "NOASSERTION"
        ],
        "licenseDeclared": "NOASSERTION",
        "copyrightText": "NOASSERTION",
        "versionInfo": "1.5.2",
        "externalRefs": [
          {
            "referenceCategory": "PACKAGE-MANAGER",
            "referenceType": "purl",
            "referenceLocator": "pkg:maven/org.junit.platform/junit-platform-commons@1.5.2"
          }
        ],
        "supplier": "NOASSERTION"
      },
      {
        "name": "com.fasterxml.jackson.datatype.jackson-datatype-jdk8",
        "SPDXID": "SPDXRef-Package-9836EA48616D2C0AC35E83B1B2BEDD25359267E1A8B0571172791C4B8553FB5B",
        "downloadLocation": "NOASSERTION",
        "filesAnalyzed": false,
        "licenseConcluded": "NOASSERTION",
        "licenseInfoFromFiles": [
          "NOASSERTION"
        ],
        "licenseDeclared": "NOASSERTION",
        "copyrightText": "NOASSERTION",
        "versionInfo": "2.10.2",
        "externalRefs": [
          {
            "referenceCategory": "PACKAGE-MANAGER",
            "referenceType": "purl",
            "referenceLocator": "pkg:maven/com.fasterxml.jackson.datatype/jackson-datatype-jdk8@2.10.2"
          }
        ],
        "supplier": "NOASSERTION"
      },
      {
        "name": "jakarta.annotation.jakarta.annotation-api",
        "SPDXID": "SPDXRef-Package-3B6E758A9B951E4BDD81112E516B1F6AA1DD66604631FEE7E036F8F96712AAC2",
        "downloadLocation": "NOASSERTION",
        "filesAnalyzed": false,
        "licenseConcluded": "NOASSERTION",
        "licenseInfoFromFiles": [
          "NOASSERTION"
        ],
        "licenseDeclared": "NOASSERTION",
        "copyrightText": "NOASSERTION",
        "versionInfo": "1.3.5",
        "externalRefs": [
          {
            "referenceCategory": "PACKAGE-MANAGER",
            "referenceType": "purl",
            "referenceLocator": "pkg:maven/jakarta.annotation/jakarta.annotation-api@1.3.5"
          }
        ],
        "supplier": "NOASSERTION"
      },
      {
        "name": "org.springframework.spring-context",
        "SPDXID": "SPDXRef-Package-D39E1F83619B38A688F2301266F5B8889099748195CAE0C3C241D2EE3959E2D8",
        "downloadLocation": "NOASSERTION",
        "filesAnalyzed": false,
        "licenseConcluded": "NOASSERTION",
        "licenseInfoFromFiles": [
          "NOASSERTION"
        ],
        "licenseDeclared": "NOASSERTION",
        "copyrightText": "NOASSERTION",
        "versionInfo": "5.2.3.RELEASE",
        "externalRefs": [
          {
            "referenceCategory": "PACKAGE-MANAGER",
            "referenceType": "purl",
            "referenceLocator": "pkg:maven/org.springframework/spring-context@5.2.3.RELEASE"
          }
        ],
        "supplier": "NOASSERTION"
      },
      {
        "name": "org.yaml.snakeyaml",
        "SPDXID": "SPDXRef-Package-168E0AF2CDC781377505F92FCD476034C8D1EDCDD0FBE93666FC6187359ECC93",
        "downloadLocation": "NOASSERTION",
        "filesAnalyzed": false,
        "licenseConcluded": "NOASSERTION",
        "licenseInfoFromFiles": [
          "NOASSERTION"
        ],
        "licenseDeclared": "NOASSERTION",
        "copyrightText": "NOASSERTION",
        "versionInfo": "1.25",
        "externalRefs": [
          {
            "referenceCategory": "PACKAGE-MANAGER",
            "referenceType": "purl",
            "referenceLocator": "pkg:maven/org.yaml/snakeyaml@1.25"
          }
        ],
        "supplier": "NOASSERTION"
      },
      {
        "name": "org.springframework.boot.spring-boot",
        "SPDXID": "SPDXRef-Package-F23EB50997069B77207202B03A8584FDD2AC2D5130AE3444D1FEB64C0BE3972A",
        "downloadLocation": "NOASSERTION",
        "filesAnalyzed": false,
        "licenseConcluded": "NOASSERTION",
        "licenseInfoFromFiles": [
          "NOASSERTION"
        ],
        "licenseDeclared": "NOASSERTION",
        "copyrightText": "NOASSERTION",
        "versionInfo": "2.2.4.RELEASE",
        "externalRefs": [
          {
            "referenceCategory": "PACKAGE-MANAGER",
            "referenceType": "purl",
            "referenceLocator": "pkg:maven/org.springframework.boot/spring-boot@2.2.4.RELEASE"
          }
        ],
        "supplier": "NOASSERTION"
      },
      {
        "name": "org.springframework.spring-test",
        "SPDXID": "SPDXRef-Package-43F9B087EC44DC9E49633D5CFAF0BA5CD87A162A7867ADE420A24B25BF325B82",
        "downloadLocation": "NOASSERTION",
        "filesAnalyzed": false,
        "licenseConcluded": "NOASSERTION",
        "licenseInfoFromFiles": [
          "NOASSERTION"
        ],
        "licenseDeclared": "NOASSERTION",
        "copyrightText": "NOASSERTION",
        "versionInfo": "5.2.3.RELEASE",
        "externalRefs": [
          {
            "referenceCategory": "PACKAGE-MANAGER",
            "referenceType": "purl",
            "referenceLocator": "pkg:maven/org.springframework/spring-test@5.2.3.RELEASE"
          }
        ],
        "supplier": "NOASSERTION"
      },
      {
        "name": "ch.qos.logback.logback-core",
        "SPDXID": "SPDXRef-Package-9DDFE43451D5A5DB1293935084FFF4750CB95C4E1B75F714C00A265897DD2EFF",
        "downloadLocation": "NOASSERTION",
        "filesAnalyzed": false,
        "licenseConcluded": "NOASSERTION",
        "licenseInfoFromFiles": [
          "NOASSERTION"
        ],
        "licenseDeclared": "NOASSERTION",
        "copyrightText": "NOASSERTION",
        "versionInfo": "1.2.3",
        "externalRefs": [
          {
            "referenceCategory": "PACKAGE-MANAGER",
            "referenceType": "purl",
            "referenceLocator": "pkg:maven/ch.qos.logback/logback-core@1.2.3"
          }
        ],
        "supplier": "NOASSERTION"
      },
      {
        "name": "org.springframework.boot.spring-boot-test-autoconfigure",
        "SPDXID": "SPDXRef-Package-CEC12B6D490DD6EBE02C7C689E0AA5559BCB2EB491F23B034196EA4587A206B2",
        "downloadLocation": "NOASSERTION",
        "filesAnalyzed": false,
        "licenseConcluded": "NOASSERTION",
        "licenseInfoFromFiles": [
          "NOASSERTION"
        ],
        "licenseDeclared": "NOASSERTION",
        "copyrightText": "NOASSERTION",
        "versionInfo": "2.2.4.RELEASE",
        "externalRefs": [
          {
            "referenceCategory": "PACKAGE-MANAGER",
            "referenceType": "purl",
            "referenceLocator": "pkg:maven/org.springframework.boot/spring-boot-test-autoconfigure@2.2.4.RELEASE"
          }
        ],
        "supplier": "NOASSERTION"
      },
      {
        "name": "org.apache.logging.log4j.log4j-to-slf4j",
        "SPDXID": "SPDXRef-Package-0779B2A10E5A1569BD407DC1F3CA1DB34664E5338D6DEE24044D04ACB1630F42",
        "downloadLocation": "NOASSERTION",
        "filesAnalyzed": false,
        "licenseConcluded": "NOASSERTION",
        "licenseInfoFromFiles": [
          "NOASSERTION"
        ],
        "licenseDeclared": "NOASSERTION",
        "copyrightText": "NOASSERTION",
        "versionInfo": "2.12.1",
        "externalRefs": [
          {
            "referenceCategory": "PACKAGE-MANAGER",
            "referenceType": "purl",
            "referenceLocator": "pkg:maven/org.apache.logging.log4j/log4j-to-slf4j@2.12.1"
          }
        ],
        "supplier": "NOASSERTION"
      },
      {
        "name": "org.xmlunit.xmlunit-core",
        "SPDXID": "SPDXRef-Package-7DAE346E77C713D445E9CB4BD06D8C23F901D87AFE1B849FF196D2E87B01ACEE",
        "downloadLocation": "NOASSERTION",
        "filesAnalyzed": false,
        "licenseConcluded": "NOASSERTION",
        "licenseInfoFromFiles": [
          "NOASSERTION"
        ],
        "licenseDeclared": "NOASSERTION",
        "copyrightText": "NOASSERTION",
        "versionInfo": "2.6.3",
        "externalRefs": [
          {
            "referenceCategory": "PACKAGE-MANAGER",
            "referenceType": "purl",
            "referenceLocator": "pkg:maven/org.xmlunit/xmlunit-core@2.6.3"
          }
        ],
        "supplier": "NOASSERTION"
      },
      {
        "name": "io.spring.concourse.releasescripts.release-scripts",
        "SPDXID": "SPDXRef-Package-55DE1ABD74D2C08428ACD25966B925F2CF715A60E2515EA45C5C6A0FD08D8431",
        "downloadLocation": "NOASSERTION",
        "filesAnalyzed": false,
        "licenseConcluded": "NOASSERTION",
        "licenseInfoFromFiles": [
          "NOASSERTION"
        ],
        "licenseDeclared": "NOASSERTION",
        "copyrightText": "NOASSERTION",
        "versionInfo": "0.0.1-SNAPSHOT",
        "externalRefs": [
          {
            "referenceCategory": "PACKAGE-MANAGER",
            "referenceType": "purl",
            "referenceLocator": "pkg:maven/io.spring.concourse.releasescripts/release-scripts@0.0.1-SNAPSHOT"
          }
        ],
        "supplier": "NOASSERTION"
      },
      {
        "name": "org.bouncycastle.bcpg-jdk18on",
        "SPDXID": "SPDXRef-Package-9B75DB966F8B4064746C86355F4CDD7E920CA6E442F090B0C29855990694B50F",
        "downloadLocation": "NOASSERTION",
        "filesAnalyzed": false,
        "licenseConcluded": "NOASSERTION",
        "licenseInfoFromFiles": [
          "NOASSERTION"
        ],
        "licenseDeclared": "NOASSERTION",
        "copyrightText": "NOASSERTION",
        "versionInfo": "1.71",
        "externalRefs": [
          {
            "referenceCategory": "PACKAGE-MANAGER",
            "referenceType": "purl",
            "referenceLocator": "pkg:maven/org.bouncycastle/bcpg-jdk18on@1.71"
          }
        ],
        "supplier": "NOASSERTION"
      },
      {
        "name": "org.springframework.boot.spring-boot-starter-logging",
        "SPDXID": "SPDXRef-Package-FAD5B5DB534D09C04A661880C5ECDC98AD1748D60700C53AE092B3462E43DC0B",
        "downloadLocation": "NOASSERTION",
        "filesAnalyzed": false,
        "licenseConcluded": "NOASSERTION",
        "licenseInfoFromFiles": [
          "NOASSERTION"
        ],
        "licenseDeclared": "NOASSERTION",
        "copyrightText": "NOASSERTION",
        "versionInfo": "2.2.4.RELEASE",
        "externalRefs": [
          {
            "referenceCategory": "PACKAGE-MANAGER",
            "referenceType": "purl",
            "referenceLocator": "pkg:maven/org.springframework.boot/spring-boot-starter-logging@2.2.4.RELEASE"
          }
        ],
        "supplier": "NOASSERTION"
      },
      {
        "name": "org.apiguardian.apiguardian-api",
        "SPDXID": "SPDXRef-Package-524FF08F7D1FB89B60096F0A543E6ACD6DB8AD1B5C3F87A1DFF0D377A59EC186",
        "downloadLocation": "NOASSERTION",
        "filesAnalyzed": false,
        "licenseConcluded": "NOASSERTION",
        "licenseInfoFromFiles": [
          "NOASSERTION"
        ],
        "licenseDeclared": "NOASSERTION",
        "copyrightText": "NOASSERTION",
        "versionInfo": "1.1.0",
        "externalRefs": [
          {
            "referenceCategory": "PACKAGE-MANAGER",
            "referenceType": "purl",
            "referenceLocator": "pkg:maven/org.apiguardian/apiguardian-api@1.1.0"
          }
        ],
        "supplier": "NOASSERTION"
      },
      {
        "name": "org.junit.jupiter.junit-jupiter-params",
        "SPDXID": "SPDXRef-Package-8217801FF3A85B05A117A7382EF3C060EA66816DBADE938BA06ABCF3538D987D",
        "downloadLocation": "NOASSERTION",
        "filesAnalyzed": false,
        "licenseConcluded": "NOASSERTION",
        "licenseInfoFromFiles": [
          "NOASSERTION"
        ],
        "licenseDeclared": "NOASSERTION",
        "copyrightText": "NOASSERTION",
        "versionInfo": "5.5.2",
        "externalRefs": [
          {
            "referenceCategory": "PACKAGE-MANAGER",
            "referenceType": "purl",
            "referenceLocator": "pkg:maven/org.junit.jupiter/junit-jupiter-params@5.5.2"
          }
        ],
        "supplier": "NOASSERTION"
      },
      {
        "name": "org.springframework.spring-expression",
        "SPDXID": "SPDXRef-Package-62C837AF7BA9409C5B6E5C5F00402D93FC4C796637C9133BCD467D28696A433D",
        "downloadLocation": "NOASSERTION",
        "filesAnalyzed": false,
        "licenseConcluded": "NOASSERTION",
        "licenseInfoFromFiles": [
          "NOASSERTION"
        ],
        "licenseDeclared": "NOASSERTION",
        "copyrightText": "NOASSERTION",
        "versionInfo": "5.2.3.RELEASE",
        "externalRefs": [
          {
            "referenceCategory": "PACKAGE-MANAGER",
            "referenceType": "purl",
            "referenceLocator": "pkg:maven/org.springframework/spring-expression@5.2.3.RELEASE"
          }
        ],
        "supplier": "NOASSERTION"
      },
      {
        "name": "com.vaadin.external.google.android-json",
        "SPDXID": "SPDXRef-Package-56952B0E904B7F9994538AE7C68EF9FF4737C4EC579787819CA5E6A04CB652C5",
        "downloadLocation": "NOASSERTION",
        "filesAnalyzed": false,
        "licenseConcluded": "NOASSERTION",
        "licenseInfoFromFiles": [
          "NOASSERTION"
        ],
        "licenseDeclared": "NOASSERTION",
        "copyrightText": "NOASSERTION",
        "versionInfo": "0.0.20131108.vaadin1",
        "externalRefs": [
          {
            "referenceCategory": "PACKAGE-MANAGER",
            "referenceType": "purl",
            "referenceLocator": "pkg:maven/com.vaadin.external.google/android-json@0.0.20131108.vaadin1"
          }
        ],
        "supplier": "NOASSERTION"
      },
      {
        "name": "org.junit.jupiter.junit-jupiter-api",
        "SPDXID": "SPDXRef-Package-C5871D254E9ED079D6E60FC6A225BA3A71961B8BFBF9D440859206C3031361F7",
        "downloadLocation": "NOASSERTION",
        "filesAnalyzed": false,
        "licenseConcluded": "NOASSERTION",
        "licenseInfoFromFiles": [
          "NOASSERTION"
        ],
        "licenseDeclared": "NOASSERTION",
        "copyrightText": "NOASSERTION",
        "versionInfo": "5.5.2",
        "externalRefs": [
          {
            "referenceCategory": "PACKAGE-MANAGER",
            "referenceType": "purl",
            "referenceLocator": "pkg:maven/org.junit.jupiter/junit-jupiter-api@5.5.2"
          }
        ],
        "supplier": "NOASSERTION"
      },
      {
        "name": "org.mockito.mockito-core",
        "SPDXID": "SPDXRef-Package-0297B261C093AD06B7417837D1E3C7EC86AA79D5366B95E5273D6847AE230220",
        "downloadLocation": "NOASSERTION",
        "filesAnalyzed": false,
        "licenseConcluded": "NOASSERTION",
        "licenseInfoFromFiles": [
          "NOASSERTION"
        ],
        "licenseDeclared": "NOASSERTION",
        "copyrightText": "NOASSERTION",
        "versionInfo": "3.1.0",
        "externalRefs": [
          {
            "referenceCategory": "PACKAGE-MANAGER",
            "referenceType": "purl",
            "referenceLocator": "pkg:maven/org.mockito/mockito-core@3.1.0"
          }
        ],
        "supplier": "NOASSERTION"
      },
      {
        "name": "org.springframework.spring-aop",
        "SPDXID": "SPDXRef-Package-132C0019CAA82AC6FAD6EB25D797D24EDEC46BB27A64DBB2374F6BDDEEF0DC03",
        "downloadLocation": "NOASSERTION",
        "filesAnalyzed": false,
        "licenseConcluded": "NOASSERTION",
        "licenseInfoFromFiles": [
          "NOASSERTION"
        ],
        "licenseDeclared": "NOASSERTION",
        "copyrightText": "NOASSERTION",
        "versionInfo": "5.2.3.RELEASE",
        "externalRefs": [
          {
            "referenceCategory": "PACKAGE-MANAGER",
            "referenceType": "purl",
            "referenceLocator": "pkg:maven/org.springframework/spring-aop@5.2.3.RELEASE"
          }
        ],
        "supplier": "NOASSERTION"
      },
      {
        "name": "org.slf4j.jul-to-slf4j",
        "SPDXID": "SPDXRef-Package-22CCFFF9B3428AF0755580AA1C4E88DBD5D33BC48CBF2E94528032DC78656902",
        "downloadLocation": "NOASSERTION",
        "filesAnalyzed": false,
        "licenseConcluded": "NOASSERTION",
        "licenseInfoFromFiles": [
          "NOASSERTION"
        ],
        "licenseDeclared": "NOASSERTION",
        "copyrightText": "NOASSERTION",
        "versionInfo": "1.7.30",
        "externalRefs": [
          {
            "referenceCategory": "PACKAGE-MANAGER",
            "referenceType": "purl",
            "referenceLocator": "pkg:maven/org.slf4j/jul-to-slf4j@1.7.30"
          }
        ],
        "supplier": "NOASSERTION"
      },
      {
        "name": "org.springframework.boot.spring-boot-autoconfigure",
        "SPDXID": "SPDXRef-Package-6CBF41F76AB96DC34AC91B28DDC863C103CDA0555EADE73A79B0F24199058B18",
        "downloadLocation": "NOASSERTION",
        "filesAnalyzed": false,
        "licenseConcluded": "NOASSERTION",
        "licenseInfoFromFiles": [
          "NOASSERTION"
        ],
        "licenseDeclared": "NOASSERTION",
        "copyrightText": "NOASSERTION",
        "versionInfo": "2.2.4.RELEASE",
        "externalRefs": [
          {
            "referenceCategory": "PACKAGE-MANAGER",
            "referenceType": "purl",
            "referenceLocator": "pkg:maven/org.springframework.boot/spring-boot-autoconfigure@2.2.4.RELEASE"
          }
        ],
        "supplier": "NOASSERTION"
      },
      {
        "name": "com.fasterxml.jackson.core.jackson-databind",
        "SPDXID": "SPDXRef-Package-35F71A9361670EFD9B2F735610388FB31428E991C959978789BBDDC87DF4EDBB",
        "downloadLocation": "NOASSERTION",
        "filesAnalyzed": false,
        "licenseConcluded": "NOASSERTION",
        "licenseInfoFromFiles": [
          "NOASSERTION"
        ],
        "licenseDeclared": "NOASSERTION",
        "copyrightText": "NOASSERTION",
        "versionInfo": "2.10.2",
        "externalRefs": [
          {
            "referenceCategory": "PACKAGE-MANAGER",
            "referenceType": "purl",
            "referenceLocator": "pkg:maven/com.fasterxml.jackson.core/jackson-databind@2.10.2"
          }
        ],
        "supplier": "NOASSERTION"
      },
      {
        "name": "org.springframework.boot.spring-boot-starter",
        "SPDXID": "SPDXRef-Package-B7DFF1F578A5C5E9BC62882A26994868C060864CE03127D20B9102E38CD52C7B",
        "downloadLocation": "NOASSERTION",
        "filesAnalyzed": false,
        "licenseConcluded": "NOASSERTION",
        "licenseInfoFromFiles": [
          "NOASSERTION"
        ],
        "licenseDeclared": "NOASSERTION",
        "copyrightText": "NOASSERTION",
        "versionInfo": "2.2.4.RELEASE",
        "externalRefs": [
          {
            "referenceCategory": "PACKAGE-MANAGER",
            "referenceType": "purl",
            "referenceLocator": "pkg:maven/org.springframework.boot/spring-boot-starter@2.2.4.RELEASE"
          }
        ],
        "supplier": "NOASSERTION"
      },
      {
        "name": "org.junit.jupiter.junit-jupiter-engine",
        "SPDXID": "SPDXRef-Package-6E18789A820F97CF46CAA1F75F359A1AB0944A0220D5ED22CA0B514AA214E9D9",
        "downloadLocation": "NOASSERTION",
        "filesAnalyzed": false,
        "licenseConcluded": "NOASSERTION",
        "licenseInfoFromFiles": [
          "NOASSERTION"
        ],
        "licenseDeclared": "NOASSERTION",
        "copyrightText": "NOASSERTION",
        "versionInfo": "5.5.2",
        "externalRefs": [
          {
            "referenceCategory": "PACKAGE-MANAGER",
            "referenceType": "purl",
            "referenceLocator": "pkg:maven/org.junit.jupiter/junit-jupiter-engine@5.5.2"
          }
        ],
        "supplier": "NOASSERTION"
      },
      {
        "name": "org.springframework.boot.spring-boot-starter-test",
        "SPDXID": "SPDXRef-Package-D234F7F57FF2BBD2413BCFF0B480568A30243C73C164092DE04DC698A2538B63",
        "downloadLocation": "NOASSERTION",
        "filesAnalyzed": false,
        "licenseConcluded": "NOASSERTION",
        "licenseInfoFromFiles": [
          "NOASSERTION"
        ],
        "licenseDeclared": "NOASSERTION",
        "copyrightText": "NOASSERTION",
        "versionInfo": "2.2.4.RELEASE",
        "externalRefs": [
          {
            "referenceCategory": "PACKAGE-MANAGER",
            "referenceType": "purl",
            "referenceLocator": "pkg:maven/org.springframework.boot/spring-boot-starter-test@2.2.4.RELEASE"
          }
        ],
        "supplier": "NOASSERTION"
      },
      {
        "name": "com.jayway.jsonpath.json-path",
        "SPDXID": "SPDXRef-Package-E91D86D60D7F578EB4B75023A864A67542E6A163C8D6B4941F658D548F8F5D23",
        "downloadLocation": "NOASSERTION",
        "filesAnalyzed": false,
        "licenseConcluded": "NOASSERTION",
        "licenseInfoFromFiles": [
          "NOASSERTION"
        ],
        "licenseDeclared": "NOASSERTION",
        "copyrightText": "NOASSERTION",
        "versionInfo": "2.4.0",
        "externalRefs": [
          {
            "referenceCategory": "PACKAGE-MANAGER",
            "referenceType": "purl",
            "referenceLocator": "pkg:maven/com.jayway.jsonpath/json-path@2.4.0"
          }
        ],
        "supplier": "NOASSERTION"
      },
      {
        "name": "org.slf4j.slf4j-api",
        "SPDXID": "SPDXRef-Package-A9C924AD79561EFB164CED418D301DD0AFDDC87F2179B97885139633C2D34961",
        "downloadLocation": "NOASSERTION",
        "filesAnalyzed": false,
        "licenseConcluded": "NOASSERTION",
        "licenseInfoFromFiles": [
          "NOASSERTION"
        ],
        "licenseDeclared": "NOASSERTION",
        "copyrightText": "NOASSERTION",
        "versionInfo": "1.7.30",
        "externalRefs": [
          {
            "referenceCategory": "PACKAGE-MANAGER",
            "referenceType": "purl",
            "referenceLocator": "pkg:maven/org.slf4j/slf4j-api@1.7.30"
          }
        ],
        "supplier": "NOASSERTION"
      },
      {
        "name": "org.opentest4j.opentest4j",
        "SPDXID": "SPDXRef-Package-2B8DC97169D40646AAD86B8F0402EF471C3DE1F226CF79A6B148F36AF31C667F",
        "downloadLocation": "NOASSERTION",
        "filesAnalyzed": false,
        "licenseConcluded": "NOASSERTION",
        "licenseInfoFromFiles": [
          "NOASSERTION"
        ],
        "licenseDeclared": "NOASSERTION",
        "copyrightText": "NOASSERTION",
        "versionInfo": "1.2.0",
        "externalRefs": [
          {
            "referenceCategory": "PACKAGE-MANAGER",
            "referenceType": "purl",
            "referenceLocator": "pkg:maven/org.opentest4j/opentest4j@1.2.0"
          }
        ],
        "supplier": "NOASSERTION"
      },
      {
        "name": "org.hamcrest.hamcrest",
        "SPDXID": "SPDXRef-Package-6D1E41E72A858B937561AFDE88EAEE9CE12E33C02E64FD3E8F61C251AD4D7E6D",
        "downloadLocation": "NOASSERTION",
        "filesAnalyzed": false,
        "licenseConcluded": "NOASSERTION",
        "licenseInfoFromFiles": [
          "NOASSERTION"
        ],
        "licenseDeclared": "NOASSERTION",
        "copyrightText": "NOASSERTION",
        "versionInfo": "2.1",
        "externalRefs": [
          {
            "referenceCategory": "PACKAGE-MANAGER",
            "referenceType": "purl",
            "referenceLocator": "pkg:maven/org.hamcrest/hamcrest@2.1"
          }
        ],
        "supplier": "NOASSERTION"
      },
      {
        "name": "org.skyscreamer.jsonassert",
        "SPDXID": "SPDXRef-Package-D638DE626A4146BFD01F7653640C9279950D6BA909566F085F22B038B8513501",
        "downloadLocation": "NOASSERTION",
        "filesAnalyzed": false,
        "licenseConcluded": "NOASSERTION",
        "licenseInfoFromFiles": [
          "NOASSERTION"
        ],
        "licenseDeclared": "NOASSERTION",
        "copyrightText": "NOASSERTION",
        "versionInfo": "1.5.0",
        "externalRefs": [
          {
            "referenceCategory": "PACKAGE-MANAGER",
            "referenceType": "purl",
            "referenceLocator": "pkg:maven/org.skyscreamer/jsonassert@1.5.0"
          }
        ],
        "supplier": "NOASSERTION"
      },
      {
        "name": "jakarta.activation.jakarta.activation-api",
        "SPDXID": "SPDXRef-Package-304105878AA833723D40E35A6EC279B267EB26890B60742AB1E35CCF074CFFD7",
        "downloadLocation": "NOASSERTION",
        "filesAnalyzed": false,
        "licenseConcluded": "NOASSERTION",
        "licenseInfoFromFiles": [
          "NOASSERTION"
        ],
        "licenseDeclared": "NOASSERTION",
        "copyrightText": "NOASSERTION",
        "versionInfo": "1.2.1",
        "externalRefs": [
          {
            "referenceCategory": "PACKAGE-MANAGER",
            "referenceType": "purl",
            "referenceLocator": "pkg:maven/jakarta.activation/jakarta.activation-api@1.2.1"
          }
        ],
        "supplier": "NOASSERTION"
      },
      {
        "name": "com.fasterxml.jackson.datatype.jackson-datatype-jsr310",
        "SPDXID": "SPDXRef-Package-1702BBB6A7D45ADFC9EE452570C829605B096FB77C60A2EC67CC0F91EFC90BB7",
        "downloadLocation": "NOASSERTION",
        "filesAnalyzed": false,
        "licenseConcluded": "NOASSERTION",
        "licenseInfoFromFiles": [
          "NOASSERTION"
        ],
        "licenseDeclared": "NOASSERTION",
        "copyrightText": "NOASSERTION",
        "versionInfo": "2.10.2",
        "externalRefs": [
          {
            "referenceCategory": "PACKAGE-MANAGER",
            "referenceType": "purl",
            "referenceLocator": "pkg:maven/com.fasterxml.jackson.datatype/jackson-datatype-jsr310@2.10.2"
          }
        ],
        "supplier": "NOASSERTION"
      },
      {
        "name": "jakarta.xml.bind.jakarta.xml.bind-api",
        "SPDXID": "SPDXRef-Package-DAA52C93B207A14A307A00173E1041DFDD1D326CCD7DF539EBE1C48581717694",
        "downloadLocation": "NOASSERTION",
        "filesAnalyzed": false,
        "licenseConcluded": "NOASSERTION",
        "licenseInfoFromFiles": [
          "NOASSERTION"
        ],
        "licenseDeclared": "NOASSERTION",
        "copyrightText": "NOASSERTION",
        "versionInfo": "2.3.2",
        "externalRefs": [
          {
            "referenceCategory": "PACKAGE-MANAGER",
            "referenceType": "purl",
            "referenceLocator": "pkg:maven/jakarta.xml.bind/jakarta.xml.bind-api@2.3.2"
          }
        ],
        "supplier": "NOASSERTION"
      },
      {
        "name": "com.fasterxml.jackson.core.jackson-annotations",
        "SPDXID": "SPDXRef-Package-35719B604BE196643C84B810B2B09A1880C5C73AEF0037B1537A6B3F644C2296",
        "downloadLocation": "NOASSERTION",
        "filesAnalyzed": false,
        "licenseConcluded": "NOASSERTION",
        "licenseInfoFromFiles": [
          "NOASSERTION"
        ],
        "licenseDeclared": "NOASSERTION",
        "copyrightText": "NOASSERTION",
        "versionInfo": "2.10.2",
        "externalRefs": [
          {
            "referenceCategory": "PACKAGE-MANAGER",
            "referenceType": "purl",
            "referenceLocator": "pkg:maven/com.fasterxml.jackson.core/jackson-annotations@2.10.2"
          }
        ],
        "supplier": "NOASSERTION"
      },
      {
        "name": "org.springframework.spring-beans",
        "SPDXID": "SPDXRef-Package-55A491D1814FA7FDF7B48A2E47549E96262FC843692811FB8918B7E2D2035F7A",
        "downloadLocation": "NOASSERTION",
        "filesAnalyzed": false,
        "licenseConcluded": "NOASSERTION",
        "licenseInfoFromFiles": [
          "NOASSERTION"
        ],
        "licenseDeclared": "NOASSERTION",
        "copyrightText": "NOASSERTION",
        "versionInfo": "5.2.3.RELEASE",
        "externalRefs": [
          {
            "referenceCategory": "PACKAGE-MANAGER",
            "referenceType": "purl",
            "referenceLocator": "pkg:maven/org.springframework/spring-beans@5.2.3.RELEASE"
          }
        ],
        "supplier": "NOASSERTION"
      },
      {
        "name": "org.mockito.mockito-junit-jupiter",
        "SPDXID": "SPDXRef-Package-D2A3D1AB36188DA09E4E02EAC6480FBB0D6B60168933D02B3286D8D16AADDFB1",
        "downloadLocation": "NOASSERTION",
        "filesAnalyzed": false,
        "licenseConcluded": "NOASSERTION",
        "licenseInfoFromFiles": [
          "NOASSERTION"
        ],
        "licenseDeclared": "NOASSERTION",
        "copyrightText": "NOASSERTION",
        "versionInfo": "3.1.0",
        "externalRefs": [
          {
            "referenceCategory": "PACKAGE-MANAGER",
            "referenceType": "purl",
            "referenceLocator": "pkg:maven/org.mockito/mockito-junit-jupiter@3.1.0"
          }
        ],
        "supplier": "NOASSERTION"
      },
      {
        "name": "org.objenesis.objenesis",
        "SPDXID": "SPDXRef-Package-065CE1AEB480C4346E3BEA263EDEB944A7760BD74A0F45C9E7A16EAD065A37C5",
        "downloadLocation": "NOASSERTION",
        "filesAnalyzed": false,
        "licenseConcluded": "NOASSERTION",
        "licenseInfoFromFiles": [
          "NOASSERTION"
        ],
        "licenseDeclared": "NOASSERTION",
        "copyrightText": "NOASSERTION",
        "versionInfo": "2.6",
        "externalRefs": [
          {
            "referenceCategory": "PACKAGE-MANAGER",
            "referenceType": "purl",
            "referenceLocator": "pkg:maven/org.objenesis/objenesis@2.6"
          }
        ],
        "supplier": "NOASSERTION"
      },
      {
        "name": "net.minidev.json-smart",
        "SPDXID": "SPDXRef-Package-05A0335B68C6F2D23C6588F4A5EB9C08BD5EC8E800D0FE7CB3CFBFBD81AD548C",
        "downloadLocation": "NOASSERTION",
        "filesAnalyzed": false,
        "licenseConcluded": "NOASSERTION",
        "licenseInfoFromFiles": [
          "NOASSERTION"
        ],
        "licenseDeclared": "NOASSERTION",
        "copyrightText": "NOASSERTION",
        "versionInfo": "2.3",
        "externalRefs": [
          {
            "referenceCategory": "PACKAGE-MANAGER",
            "referenceType": "purl",
            "referenceLocator": "pkg:maven/net.minidev/json-smart@2.3"
          }
        ],
        "supplier": "NOASSERTION"
      },
      {
        "name": "org.springframework.spring-web",
        "SPDXID": "SPDXRef-Package-A4ED58C2D355CE31A241F39218A8376D87E69594636359048FAB2AD6D5F9CE92",
        "downloadLocation": "NOASSERTION",
        "filesAnalyzed": false,
        "licenseConcluded": "NOASSERTION",
        "licenseInfoFromFiles": [
          "NOASSERTION"
        ],
        "licenseDeclared": "NOASSERTION",
        "copyrightText": "NOASSERTION",
        "versionInfo": "5.2.3.RELEASE",
        "externalRefs": [
          {
            "referenceCategory": "PACKAGE-MANAGER",
            "referenceType": "purl",
            "referenceLocator": "pkg:maven/org.springframework/spring-web@5.2.3.RELEASE"
          }
        ],
        "supplier": "NOASSERTION"
      },
      {
        "name": "com.fasterxml.jackson.core.jackson-core",
        "SPDXID": "SPDXRef-Package-93DD383DFBB0F9C72031C1349D0AF8FA644A70CCEA18F1CDCB1C113EDF1EDE5E",
        "downloadLocation": "NOASSERTION",
        "filesAnalyzed": false,
        "licenseConcluded": "NOASSERTION",
        "licenseInfoFromFiles": [
          "NOASSERTION"
        ],
        "licenseDeclared": "NOASSERTION",
        "copyrightText": "NOASSERTION",
        "versionInfo": "2.10.2",
        "externalRefs": [
          {
            "referenceCategory": "PACKAGE-MANAGER",
            "referenceType": "purl",
            "referenceLocator": "pkg:maven/com.fasterxml.jackson.core/jackson-core@2.10.2"
          }
        ],
        "supplier": "NOASSERTION"
      },
      {
        "name": "net.minidev.accessors-smart",
        "SPDXID": "SPDXRef-Package-CDB4F18BA50226654BA7D4E1F2DABE9AEBE4CC28D8BFF841097F92B4C848C483",
        "downloadLocation": "NOASSERTION",
        "filesAnalyzed": false,
        "licenseConcluded": "NOASSERTION",
        "licenseInfoFromFiles": [
          "NOASSERTION"
        ],
        "licenseDeclared": "NOASSERTION",
        "copyrightText": "NOASSERTION",
        "versionInfo": "1.2",
        "externalRefs": [
          {
            "referenceCategory": "PACKAGE-MANAGER",
            "referenceType": "purl",
            "referenceLocator": "pkg:maven/net.minidev/accessors-smart@1.2"
          }
        ],
        "supplier": "NOASSERTION"
      },
      {
        "name": "org.awaitility.awaitility",
        "SPDXID": "SPDXRef-Package-513418EDE92F4423F1ADF05AAD2417F7C4EA41CE4D22605C3DE56AFBAF249C8A",
        "downloadLocation": "NOASSERTION",
        "filesAnalyzed": false,
        "licenseConcluded": "NOASSERTION",
        "licenseInfoFromFiles": [
          "NOASSERTION"
        ],
        "licenseDeclared": "NOASSERTION",
        "copyrightText": "NOASSERTION",
        "versionInfo": "4.0.2",
        "externalRefs": [
          {
            "referenceCategory": "PACKAGE-MANAGER",
            "referenceType": "purl",
            "referenceLocator": "pkg:maven/org.awaitility/awaitility@4.0.2"
          }
        ],
        "supplier": "NOASSERTION"
      },
      {
        "name": "com.fasterxml.jackson.module.jackson-module-parameter-names",
        "SPDXID": "SPDXRef-Package-17B013DE0C4106F57D5DFE17513B71AE1ED221A7B443216678B7D1DE12DE5814",
        "downloadLocation": "NOASSERTION",
        "filesAnalyzed": false,
        "licenseConcluded": "NOASSERTION",
        "licenseInfoFromFiles": [
          "NOASSERTION"
        ],
        "licenseDeclared": "NOASSERTION",
        "copyrightText": "NOASSERTION",
        "versionInfo": "2.10.2",
        "externalRefs": [
          {
            "referenceCategory": "PACKAGE-MANAGER",
            "referenceType": "purl",
            "referenceLocator": "pkg:maven/com.fasterxml.jackson.module/jackson-module-parameter-names@2.10.2"
          }
        ],
        "supplier": "NOASSERTION"
      },
      {
        "name": "spring-boot",
        "SPDXID": "SPDXRef-RootPackage",
        "downloadLocation": "NOASSERTION",
        "packageVerificationCode": {
          "packageVerificationCodeValue": "da39a3ee5e6b4b0d3255bfef95601890afd80709"
        },
        "filesAnalyzed": true,
        "licenseConcluded": "NOASSERTION",
        "licenseInfoFromFiles": [
          "NOASSERTION"
        ],
        "licenseDeclared": "NOASSERTION",
        "copyrightText": "NOASSERTION",
        "versionInfo": "v3.2.0-M1",
        "supplier": "Organization: Be-Secure community Lab",
        "hasFiles": []
      }
    ],
    "externalDocumentRefs": [],
    "relationships": [
      {
        "relationshipType": "DESCRIBES",
        "relatedSpdxElement": "SPDXRef-RootPackage",
        "spdxElementId": "SPDXRef-DOCUMENT"
      },
      {
        "relationshipType": "DEPENDS_ON",
        "relatedSpdxElement": "SPDXRef-Package-D2A3D1AB36188DA09E4E02EAC6480FBB0D6B60168933D02B3286D8D16AADDFB1",
        "spdxElementId": "SPDXRef-RootPackage"
      },
      {
        "relationshipType": "DEPENDS_ON",
        "relatedSpdxElement": "SPDXRef-Package-55A491D1814FA7FDF7B48A2E47549E96262FC843692811FB8918B7E2D2035F7A",
        "spdxElementId": "SPDXRef-RootPackage"
      },
      {
        "relationshipType": "DEPENDS_ON",
        "relatedSpdxElement": "SPDXRef-Package-35719B604BE196643C84B810B2B09A1880C5C73AEF0037B1537A6B3F644C2296",
        "spdxElementId": "SPDXRef-RootPackage"
      },
      {
        "relationshipType": "DEPENDS_ON",
        "relatedSpdxElement": "SPDXRef-Package-DAA52C93B207A14A307A00173E1041DFDD1D326CCD7DF539EBE1C48581717694",
        "spdxElementId": "SPDXRef-RootPackage"
      },
      {
        "relationshipType": "DEPENDS_ON",
        "relatedSpdxElement": "SPDXRef-Package-1702BBB6A7D45ADFC9EE452570C829605B096FB77C60A2EC67CC0F91EFC90BB7",
        "spdxElementId": "SPDXRef-RootPackage"
      },
      {
        "relationshipType": "DEPENDS_ON",
        "relatedSpdxElement": "SPDXRef-Package-304105878AA833723D40E35A6EC279B267EB26890B60742AB1E35CCF074CFFD7",
        "spdxElementId": "SPDXRef-RootPackage"
      },
      {
        "relationshipType": "DEPENDS_ON",
        "relatedSpdxElement": "SPDXRef-Package-D638DE626A4146BFD01F7653640C9279950D6BA909566F085F22B038B8513501",
        "spdxElementId": "SPDXRef-RootPackage"
      },
      {
        "relationshipType": "DEPENDS_ON",
        "relatedSpdxElement": "SPDXRef-Package-62C837AF7BA9409C5B6E5C5F00402D93FC4C796637C9133BCD467D28696A433D",
        "spdxElementId": "SPDXRef-RootPackage"
      },
      {
        "relationshipType": "DEPENDS_ON",
        "relatedSpdxElement": "SPDXRef-Package-8217801FF3A85B05A117A7382EF3C060EA66816DBADE938BA06ABCF3538D987D",
        "spdxElementId": "SPDXRef-RootPackage"
      },
      {
        "relationshipType": "DEPENDS_ON",
        "relatedSpdxElement": "SPDXRef-Package-524FF08F7D1FB89B60096F0A543E6ACD6DB8AD1B5C3F87A1DFF0D377A59EC186",
        "spdxElementId": "SPDXRef-RootPackage"
      },
      {
        "relationshipType": "DEPENDS_ON",
        "relatedSpdxElement": "SPDXRef-Package-FAD5B5DB534D09C04A661880C5ECDC98AD1748D60700C53AE092B3462E43DC0B",
        "spdxElementId": "SPDXRef-RootPackage"
      },
      {
        "relationshipType": "DEPENDS_ON",
        "relatedSpdxElement": "SPDXRef-Package-9B75DB966F8B4064746C86355F4CDD7E920CA6E442F090B0C29855990694B50F",
        "spdxElementId": "SPDXRef-RootPackage"
      },
      {
        "relationshipType": "DEPENDS_ON",
        "relatedSpdxElement": "SPDXRef-Package-55DE1ABD74D2C08428ACD25966B925F2CF715A60E2515EA45C5C6A0FD08D8431",
        "spdxElementId": "SPDXRef-RootPackage"
      },
      {
        "relationshipType": "DEPENDS_ON",
        "relatedSpdxElement": "SPDXRef-Package-7DAE346E77C713D445E9CB4BD06D8C23F901D87AFE1B849FF196D2E87B01ACEE",
        "spdxElementId": "SPDXRef-RootPackage"
      },
      {
        "relationshipType": "DEPENDS_ON",
        "relatedSpdxElement": "SPDXRef-Package-0779B2A10E5A1569BD407DC1F3CA1DB34664E5338D6DEE24044D04ACB1630F42",
        "spdxElementId": "SPDXRef-RootPackage"
      },
      {
        "relationshipType": "DEPENDS_ON",
        "relatedSpdxElement": "SPDXRef-Package-17B013DE0C4106F57D5DFE17513B71AE1ED221A7B443216678B7D1DE12DE5814",
        "spdxElementId": "SPDXRef-RootPackage"
      },
      {
        "relationshipType": "DEPENDS_ON",
        "relatedSpdxElement": "SPDXRef-Package-513418EDE92F4423F1ADF05AAD2417F7C4EA41CE4D22605C3DE56AFBAF249C8A",
        "spdxElementId": "SPDXRef-RootPackage"
      },
      {
        "relationshipType": "DEPENDS_ON",
        "relatedSpdxElement": "SPDXRef-Package-CDB4F18BA50226654BA7D4E1F2DABE9AEBE4CC28D8BFF841097F92B4C848C483",
        "spdxElementId": "SPDXRef-RootPackage"
      },
      {
        "relationshipType": "DEPENDS_ON",
        "relatedSpdxElement": "SPDXRef-Package-93DD383DFBB0F9C72031C1349D0AF8FA644A70CCEA18F1CDCB1C113EDF1EDE5E",
        "spdxElementId": "SPDXRef-RootPackage"
      },
      {
        "relationshipType": "DEPENDS_ON",
        "relatedSpdxElement": "SPDXRef-Package-A4ED58C2D355CE31A241F39218A8376D87E69594636359048FAB2AD6D5F9CE92",
        "spdxElementId": "SPDXRef-RootPackage"
      },
      {
        "relationshipType": "DEPENDS_ON",
        "relatedSpdxElement": "SPDXRef-Package-05A0335B68C6F2D23C6588F4A5EB9C08BD5EC8E800D0FE7CB3CFBFBD81AD548C",
        "spdxElementId": "SPDXRef-RootPackage"
      },
      {
        "relationshipType": "DEPENDS_ON",
        "relatedSpdxElement": "SPDXRef-Package-065CE1AEB480C4346E3BEA263EDEB944A7760BD74A0F45C9E7A16EAD065A37C5",
        "spdxElementId": "SPDXRef-RootPackage"
      },
      {
        "relationshipType": "DEPENDS_ON",
        "relatedSpdxElement": "SPDXRef-Package-CEC12B6D490DD6EBE02C7C689E0AA5559BCB2EB491F23B034196EA4587A206B2",
        "spdxElementId": "SPDXRef-RootPackage"
      },
      {
        "relationshipType": "DEPENDS_ON",
        "relatedSpdxElement": "SPDXRef-Package-9DDFE43451D5A5DB1293935084FFF4750CB95C4E1B75F714C00A265897DD2EFF",
        "spdxElementId": "SPDXRef-RootPackage"
      },
      {
        "relationshipType": "DEPENDS_ON",
        "relatedSpdxElement": "SPDXRef-Package-43F9B087EC44DC9E49633D5CFAF0BA5CD87A162A7867ADE420A24B25BF325B82",
        "spdxElementId": "SPDXRef-RootPackage"
      },
      {
        "relationshipType": "DEPENDS_ON",
        "relatedSpdxElement": "SPDXRef-Package-F23EB50997069B77207202B03A8584FDD2AC2D5130AE3444D1FEB64C0BE3972A",
        "spdxElementId": "SPDXRef-RootPackage"
      },
      {
        "relationshipType": "DEPENDS_ON",
        "relatedSpdxElement": "SPDXRef-Package-168E0AF2CDC781377505F92FCD476034C8D1EDCDD0FBE93666FC6187359ECC93",
        "spdxElementId": "SPDXRef-RootPackage"
      },
      {
        "relationshipType": "DEPENDS_ON",
        "relatedSpdxElement": "SPDXRef-Package-D39E1F83619B38A688F2301266F5B8889099748195CAE0C3C241D2EE3959E2D8",
        "spdxElementId": "SPDXRef-RootPackage"
      },
      {
        "relationshipType": "DEPENDS_ON",
        "relatedSpdxElement": "SPDXRef-Package-3B6E758A9B951E4BDD81112E516B1F6AA1DD66604631FEE7E036F8F96712AAC2",
        "spdxElementId": "SPDXRef-RootPackage"
      },
      {
        "relationshipType": "DEPENDS_ON",
        "relatedSpdxElement": "SPDXRef-Package-6D1E41E72A858B937561AFDE88EAEE9CE12E33C02E64FD3E8F61C251AD4D7E6D",
        "spdxElementId": "SPDXRef-RootPackage"
      },
      {
        "relationshipType": "DEPENDS_ON",
        "relatedSpdxElement": "SPDXRef-Package-2B8DC97169D40646AAD86B8F0402EF471C3DE1F226CF79A6B148F36AF31C667F",
        "spdxElementId": "SPDXRef-RootPackage"
      },
      {
        "relationshipType": "DEPENDS_ON",
        "relatedSpdxElement": "SPDXRef-Package-A9C924AD79561EFB164CED418D301DD0AFDDC87F2179B97885139633C2D34961",
        "spdxElementId": "SPDXRef-RootPackage"
      },
      {
        "relationshipType": "DEPENDS_ON",
        "relatedSpdxElement": "SPDXRef-Package-E91D86D60D7F578EB4B75023A864A67542E6A163C8D6B4941F658D548F8F5D23",
        "spdxElementId": "SPDXRef-RootPackage"
      },
      {
        "relationshipType": "DEPENDS_ON",
        "relatedSpdxElement": "SPDXRef-Package-D234F7F57FF2BBD2413BCFF0B480568A30243C73C164092DE04DC698A2538B63",
        "spdxElementId": "SPDXRef-RootPackage"
      },
      {
        "relationshipType": "DEPENDS_ON",
        "relatedSpdxElement": "SPDXRef-Package-6E18789A820F97CF46CAA1F75F359A1AB0944A0220D5ED22CA0B514AA214E9D9",
        "spdxElementId": "SPDXRef-RootPackage"
      },
      {
        "relationshipType": "DEPENDS_ON",
        "relatedSpdxElement": "SPDXRef-Package-B7DFF1F578A5C5E9BC62882A26994868C060864CE03127D20B9102E38CD52C7B",
        "spdxElementId": "SPDXRef-RootPackage"
      },
      {
        "relationshipType": "DEPENDS_ON",
        "relatedSpdxElement": "SPDXRef-Package-9836EA48616D2C0AC35E83B1B2BEDD25359267E1A8B0571172791C4B8553FB5B",
        "spdxElementId": "SPDXRef-RootPackage"
      },
      {
        "relationshipType": "DEPENDS_ON",
        "relatedSpdxElement": "SPDXRef-Package-D688F8F3C0920FC253AB04DA89676A6EAABDF19EFAA12C1F88D484B18F0C6C4A",
        "spdxElementId": "SPDXRef-RootPackage"
      },
      {
        "relationshipType": "DEPENDS_ON",
        "relatedSpdxElement": "SPDXRef-Package-5B6C31B74437D07CE6B95C02E958898842139D0E60921BA2F5EEC228FA367AE2",
        "spdxElementId": "SPDXRef-RootPackage"
      },
      {
        "relationshipType": "DEPENDS_ON",
        "relatedSpdxElement": "SPDXRef-Package-7CEC26E8F875C5306D34A7D6455348CC7BF504AEE3FA259B6C16D9F2239BCE1A",
        "spdxElementId": "SPDXRef-RootPackage"
      },
      {
        "relationshipType": "DEPENDS_ON",
        "relatedSpdxElement": "SPDXRef-Package-AF61F230B02D2ADDB9CE830578142294C95805C33902ABAD4E77FD6CEA2813AA",
        "spdxElementId": "SPDXRef-RootPackage"
      },
      {
        "relationshipType": "DEPENDS_ON",
        "relatedSpdxElement": "SPDXRef-Package-CE2645995E7C5D35374354BB83B4EC929C6FF4F5E8879940AE82DFCB85A25E06",
        "spdxElementId": "SPDXRef-RootPackage"
      },
      {
        "relationshipType": "DEPENDS_ON",
        "relatedSpdxElement": "SPDXRef-Package-E5EAD97FB2A2318163EE05FA2622DBC7676D40631520E94F276C1576999F7364",
        "spdxElementId": "SPDXRef-RootPackage"
      },
      {
        "relationshipType": "DEPENDS_ON",
        "relatedSpdxElement": "SPDXRef-Package-35F71A9361670EFD9B2F735610388FB31428E991C959978789BBDDC87DF4EDBB",
        "spdxElementId": "SPDXRef-RootPackage"
      },
      {
        "relationshipType": "DEPENDS_ON",
        "relatedSpdxElement": "SPDXRef-Package-6CBF41F76AB96DC34AC91B28DDC863C103CDA0555EADE73A79B0F24199058B18",
        "spdxElementId": "SPDXRef-RootPackage"
      },
      {
        "relationshipType": "DEPENDS_ON",
        "relatedSpdxElement": "SPDXRef-Package-22CCFFF9B3428AF0755580AA1C4E88DBD5D33BC48CBF2E94528032DC78656902",
        "spdxElementId": "SPDXRef-RootPackage"
      },
      {
        "relationshipType": "DEPENDS_ON",
        "relatedSpdxElement": "SPDXRef-Package-132C0019CAA82AC6FAD6EB25D797D24EDEC46BB27A64DBB2374F6BDDEEF0DC03",
        "spdxElementId": "SPDXRef-RootPackage"
      },
      {
        "relationshipType": "DEPENDS_ON",
        "relatedSpdxElement": "SPDXRef-Package-0297B261C093AD06B7417837D1E3C7EC86AA79D5366B95E5273D6847AE230220",
        "spdxElementId": "SPDXRef-RootPackage"
      },
      {
        "relationshipType": "DEPENDS_ON",
        "relatedSpdxElement": "SPDXRef-Package-C5871D254E9ED079D6E60FC6A225BA3A71961B8BFBF9D440859206C3031361F7",
        "spdxElementId": "SPDXRef-RootPackage"
      },
      {
        "relationshipType": "DEPENDS_ON",
        "relatedSpdxElement": "SPDXRef-Package-56952B0E904B7F9994538AE7C68EF9FF4737C4EC579787819CA5E6A04CB652C5",
        "spdxElementId": "SPDXRef-RootPackage"
      },
      {
        "relationshipType": "DEPENDS_ON",
        "relatedSpdxElement": "SPDXRef-Package-71B92262C7455B6A4AB5733D7985F52D83DAEFDD6AB2C12AB0D4BDFEC92D7FC2",
        "spdxElementId": "SPDXRef-RootPackage"
      },
      {
        "relationshipType": "DEPENDS_ON",
        "relatedSpdxElement": "SPDXRef-Package-64C75A94B9FCF2899ACD501FA1AE605994B8915213C05F9A7633FCB7AAC6DDDC",
        "spdxElementId": "SPDXRef-RootPackage"
      },
      {
        "relationshipType": "DEPENDS_ON",
        "relatedSpdxElement": "SPDXRef-Package-87901215DA3F8AD2F8ED55D8DAFCC24E14227D5098FD1E7CC6B833C8BBAF3E3F",
        "spdxElementId": "SPDXRef-RootPackage"
      },
      {
        "relationshipType": "DEPENDS_ON",
        "relatedSpdxElement": "SPDXRef-Package-34570F7131A006073C0E15AB766CD5A79255D6DE2A0EDEF69D9B9DADABDEC1A8",
        "spdxElementId": "SPDXRef-RootPackage"
      },
      {
        "relationshipType": "DEPENDS_ON",
        "relatedSpdxElement": "SPDXRef-Package-4CD6BEF9A21ECD30039D25C5DEF23A397FADE5780C77CA826CEDF184C85349BE",
        "spdxElementId": "SPDXRef-RootPackage"
      },
      {
        "relationshipType": "DEPENDS_ON",
        "relatedSpdxElement": "SPDXRef-Package-6BA79E403F10E4FF19D0C4CB2C0CAFA2286576C9CA9A034316A51B250B320615",
        "spdxElementId": "SPDXRef-RootPackage"
      },
      {
        "relationshipType": "DEPENDS_ON",
        "relatedSpdxElement": "SPDXRef-Package-0F126D72864910ABE25F0A871B04597782185F8AB802C3AB9580F4FB8A550CB5",
        "spdxElementId": "SPDXRef-RootPackage"
      }
    ],
    "spdxVersion": "SPDX-2.2",
    "dataLicense": "CC0-1.0",
    "SPDXID": "SPDXRef-DOCUMENT",
    "name": "spring-boot v3.2.0-M1",
    "documentNamespace": "https://github.com/Be-Secure/spring-boot.git/spring-boot/v3.2.0-M1/uqU03oDzjkmzHFuU3WIsLw",
    "creationInfo": {
      "created": "2023-08-02T06:02:47Z",
      "creators": [
        "Organization: Be-Secure community Lab",
        "Tool: Microsoft.SBOMTool-0.3.3"
      ]
    },
    "documentDescribes": [
      "SPDXRef-RootPackage"
    ]
  }