{
  "files": [],
  "packages": [
    {
      "name": "golang.org/x/net",
      "SPDXID": "SPDXRef-Package-59CE747D5453EE558EB7F51BA35C3CE530AADB9FCAAB76B60E84C90C5A363E60",
      "downloadLocation": "NOASSERTION",
      "filesAnalyzed": false,
      "licenseConcluded": "NOASSERTION",
      "licenseDeclared": "NOASSERTION",
      "copyrightText": "NOASSERTION",
      "versionInfo": "v0.0.0-20190620200207-3b0461eec859",
      "externalRefs": [
        {
          "referenceCategory": "PACKAGE-MANAGER",
          "referenceType": "purl",
          "referenceLocator": "pkg:golang/golang.org/x/net@h1:z5CRVTTTmAJ677TzLLGU+0bjPO0LkuOLi4/5GtJWs/s="
        }
      ],
      "supplier": "NOASSERTION"
    },
    {
      "name": "github.com/kisielk/errcheck",
      "SPDXID": "SPDXRef-Package-C5E29D9DF974E203A724C506B3748F05E11C5233AE758A7504C0F0238120DF30",
      "downloadLocation": "NOASSERTION",
      "filesAnalyzed": false,
      "licenseConcluded": "NOASSERTION",
      "licenseDeclared": "NOASSERTION",
      "copyrightText": "NOASSERTION",
      "versionInfo": "v1.5.0",
      "externalRefs": [
        {
          "referenceCategory": "PACKAGE-MANAGER",
          "referenceType": "purl",
          "referenceLocator": "pkg:golang/github.com/kisielk/errcheck@h1:pFxgyoBC7bSaBwPgfKdkLd5X25qrDl4LWUI2bnpBCr8="
        }
      ],
      "supplier": "NOASSERTION"
    },
    {
      "name": "golang.org/x/tools",
      "SPDXID": "SPDXRef-Package-0F55AA864794331F872752E9E131DA1A574DBE2C04DB29EAC15CDF0B23DDE19D",
      "downloadLocation": "NOASSERTION",
      "filesAnalyzed": false,
      "licenseConcluded": "NOASSERTION",
      "licenseDeclared": "NOASSERTION",
      "copyrightText": "NOASSERTION",
      "versionInfo": "v0.0.0-20200619180055-7c47624df98f",
      "externalRefs": [
        {
          "referenceCategory": "PACKAGE-MANAGER",
          "referenceType": "purl",
          "referenceLocator": "pkg:golang/golang.org/x/tools@h1:EkVYQZoAsY45+roYkvgYkIh4xh/qjgUK9TdY2XT94GE="
        }
      ],
      "supplier": "NOASSERTION"
    },
    {
      "name": "golang.org/x/xerrors",
      "SPDXID": "SPDXRef-Package-E64D2F572F330E927B54ADED99252A8365D3EDDAF28A0A35B986E4B6CCC1D4F8",
      "downloadLocation": "NOASSERTION",
      "filesAnalyzed": false,
      "licenseConcluded": "NOASSERTION",
      "licenseDeclared": "NOASSERTION",
      "copyrightText": "NOASSERTION",
      "versionInfo": "v0.0.0-20191204190536-9bdfabe68543",
      "externalRefs": [
        {
          "referenceCategory": "PACKAGE-MANAGER",
          "referenceType": "purl",
          "referenceLocator": "pkg:golang/golang.org/x/xerrors@h1:I/5z698sn9Ka8TeJc9MKroUUfqBBauWjQqLJ2OPfmY0="
        }
      ],
      "supplier": "NOASSERTION"
    },
    {
      "name": "github.com/kr/text",
      "SPDXID": "SPDXRef-Package-6E9661E46BCA09709A7B1AE3FF28BD73BB413D713FC7E81F4FFF417C1BA86B46",
      "downloadLocation": "NOASSERTION",
      "filesAnalyzed": false,
      "licenseConcluded": "NOASSERTION",
      "licenseDeclared": "NOASSERTION",
      "copyrightText": "NOASSERTION",
      "versionInfo": "v0.2.0",
      "externalRefs": [
        {
          "referenceCategory": "PACKAGE-MANAGER",
          "referenceType": "purl",
          "referenceLocator": "pkg:golang/github.com/kr/text@h1:5Nx0Ya0ZqY2ygV366QzturHI13Jq95ApcVaJBhpS+AY="
        }
      ],
      "supplier": "NOASSERTION"
    },
    {
      "name": "golang.org/x/net",
      "SPDXID": "SPDXRef-Package-3E43D1393BFB13A294DA3CC1EC1C13F1D02C909DC656C2BCCD7CAD6D0FE83D58",
      "downloadLocation": "NOASSERTION",
      "filesAnalyzed": false,
      "licenseConcluded": "NOASSERTION",
      "licenseDeclared": "NOASSERTION",
      "copyrightText": "NOASSERTION",
      "versionInfo": "v0.0.0-20200226121028-0de0cce0169b",
      "externalRefs": [
        {
          "referenceCategory": "PACKAGE-MANAGER",
          "referenceType": "purl",
          "referenceLocator": "pkg:golang/golang.org/x/net@h1:z5CRVTTTmAJ677TzLLGU+0bjPO0LkuOLi4/5GtJWs/s="
        }
      ],
      "supplier": "NOASSERTION"
    },
    {
      "name": "github.com/kisielk/gotool",
      "SPDXID": "SPDXRef-Package-37ED6C4EA8447BD84469A5BA731FCE918BFC31EC55E4565BDE8B09D1542C2637",
      "downloadLocation": "NOASSERTION",
      "filesAnalyzed": false,
      "licenseConcluded": "NOASSERTION",
      "licenseDeclared": "NOASSERTION",
      "copyrightText": "NOASSERTION",
      "versionInfo": "v1.0.0",
      "externalRefs": [
        {
          "referenceCategory": "PACKAGE-MANAGER",
          "referenceType": "purl",
          "referenceLocator": "pkg:golang/github.com/kisielk/gotool@h1:XhKaO+MFFWcvkIS/tQcRk01m1F5IRFswLeQ+oQHNcck="
        }
      ],
      "supplier": "NOASSERTION"
    },
    {
      "name": "sigs.k8s.io/json",
      "SPDXID": "SPDXRef-Package-D8CC961206AD62D4F2E7308905CD165870BA7B3D1FEB82358412CFDB67FA5F33",
      "downloadLocation": "NOASSERTION",
      "filesAnalyzed": false,
      "licenseConcluded": "NOASSERTION",
      "licenseDeclared": "NOASSERTION",
      "copyrightText": "NOASSERTION",
      "versionInfo": "v0.0.0-20221116044647-bc3834ca7abd",
      "externalRefs": [
        {
          "referenceCategory": "PACKAGE-MANAGER",
          "referenceType": "purl",
          "referenceLocator": "pkg:golang/sigs.k8s.io/json@h1:EDPBXCAspyGV4jQlpZSudPeMmr1bNJefnuqLsRAsHZo="
        }
      ],
      "supplier": "NOASSERTION"
    },
    {
      "name": "github.com/creack/pty",
      "SPDXID": "SPDXRef-Package-FD31658756AFAF5E40E70A899F3D58DF8B433A3836216CA99C9EB523BBB8B82A",
      "downloadLocation": "NOASSERTION",
      "filesAnalyzed": false,
      "licenseConcluded": "NOASSERTION",
      "licenseDeclared": "NOASSERTION",
      "copyrightText": "NOASSERTION",
      "versionInfo": "v1.1.9",
      "externalRefs": [
        {
          "referenceCategory": "PACKAGE-MANAGER",
          "referenceType": "purl",
          "referenceLocator": "pkg:golang/github.com/creack/pty@h1:oKZEueFk5CKHvIhNR5MUki03XCEU+Q6VDXinZuGJ33E="
        }
      ],
      "supplier": "NOASSERTION"
    },
    {
      "name": "golang.org/x/sync",
      "SPDXID": "SPDXRef-Package-7A19B52E8F896DB3BED127884BD6019DD768CE9CCC37946BA4A0EC82B7734049",
      "downloadLocation": "NOASSERTION",
      "filesAnalyzed": false,
      "licenseConcluded": "NOASSERTION",
      "licenseDeclared": "NOASSERTION",
      "copyrightText": "NOASSERTION",
      "versionInfo": "v0.0.0-20190911185100-cd5d95a43a6e",
      "externalRefs": [
        {
          "referenceCategory": "PACKAGE-MANAGER",
          "referenceType": "purl",
          "referenceLocator": "pkg:golang/golang.org/x/sync@h1:RxMgew5VJxzue5/jJTE5uejpjVlOe/izrB70Jof72aM="
        }
      ],
      "supplier": "NOASSERTION"
    },
    {
      "name": "gopkg.in/inf.v0",
      "SPDXID": "SPDXRef-Package-54752A2D05C113E904C18C1CAAD62C2236CEBD089CC561706EDA4429B4E37FC8",
      "downloadLocation": "NOASSERTION",
      "filesAnalyzed": false,
      "licenseConcluded": "NOASSERTION",
      "licenseDeclared": "NOASSERTION",
      "copyrightText": "NOASSERTION",
      "versionInfo": "v0.9.1",
      "externalRefs": [
        {
          "referenceCategory": "PACKAGE-MANAGER",
          "referenceType": "purl",
          "referenceLocator": "pkg:golang/gopkg.in/inf.v0@h1:73M5CoZyi3ZLMOyDlQh031Cx6N9NDJ2Vvfl76EDAgDc="
        }
      ],
      "supplier": "NOASSERTION"
    },
    {
      "name": "golang.org/x/sys",
      "SPDXID": "SPDXRef-Package-4DAD0C8B67FB1629FA51ADC4F3B687F7E8956EE6EF103092AED3BF607E477402",
      "downloadLocation": "NOASSERTION",
      "filesAnalyzed": false,
      "licenseConcluded": "NOASSERTION",
      "licenseDeclared": "NOASSERTION",
      "copyrightText": "NOASSERTION",
      "versionInfo": "v0.0.0-20190215142949-d0b11bdaac8a",
      "externalRefs": [
        {
          "referenceCategory": "PACKAGE-MANAGER",
          "referenceType": "purl",
          "referenceLocator": "pkg:golang/golang.org/x/sys@h1:STP8DvDyc/dI5b8T5hshtkjS+E42TnysNCUPdjciGhY="
        }
      ],
      "supplier": "NOASSERTION"
    },
    {
      "name": "github.com/spf13/pflag",
      "SPDXID": "SPDXRef-Package-6F6D35D97F7FAD2044E3A76DD804FAA777D2FCFE708930657ACD9B72D32F637F",
      "downloadLocation": "NOASSERTION",
      "filesAnalyzed": false,
      "licenseConcluded": "NOASSERTION",
      "licenseDeclared": "NOASSERTION",
      "copyrightText": "NOASSERTION",
      "versionInfo": "v1.0.5",
      "externalRefs": [
        {
          "referenceCategory": "PACKAGE-MANAGER",
          "referenceType": "purl",
          "referenceLocator": "pkg:golang/github.com/spf13/pflag@h1:iy+VFUOCP1a+8yFto/drg2CJ5u0yRoB7fZw3DKv/JXA="
        }
      ],
      "supplier": "NOASSERTION"
    },
    {
      "name": "sigs.k8s.io/yaml",
      "SPDXID": "SPDXRef-Package-88F9FB27AC142FAC8F1E4FE333AE03873283A2B359795059A076DD0E7C47DA57",
      "downloadLocation": "NOASSERTION",
      "filesAnalyzed": false,
      "licenseConcluded": "NOASSERTION",
      "licenseDeclared": "NOASSERTION",
      "copyrightText": "NOASSERTION",
      "versionInfo": "v1.3.0",
      "externalRefs": [
        {
          "referenceCategory": "PACKAGE-MANAGER",
          "referenceType": "purl",
          "referenceLocator": "pkg:golang/sigs.k8s.io/yaml@h1:a2VclLzOGrwOHDiV8EfBGhvjHvP46CtW5j6POvhYGGo="
        }
      ],
      "supplier": "NOASSERTION"
    },
    {
      "name": "sigs.k8s.io/structured-merge-diff/v4",
      "SPDXID": "SPDXRef-Package-B4121D75D3C0345AE8DC9C682DDA3F17487EFE49ED55F4C9BE31C5132A516695",
      "downloadLocation": "NOASSERTION",
      "filesAnalyzed": false,
      "licenseConcluded": "NOASSERTION",
      "licenseDeclared": "NOASSERTION",
      "copyrightText": "NOASSERTION",
      "versionInfo": "v4.4.1",
      "externalRefs": [
        {
          "referenceCategory": "PACKAGE-MANAGER",
          "referenceType": "purl",
          "referenceLocator": "pkg:golang/sigs.k8s.io/structured-merge-diff/v4@h1:150L+0vs/8DA78h1u02ooW1/fFq/Lwr+sGiqlzvrtq4="
        }
      ],
      "supplier": "NOASSERTION"
    },
    {
      "name": "golang.org/x/xerrors",
      "SPDXID": "SPDXRef-Package-7F7E31A05F83564D6B28A95727EC3CF6C559093084BE16DB4E531A87FEF82825",
      "downloadLocation": "NOASSERTION",
      "filesAnalyzed": false,
      "licenseConcluded": "NOASSERTION",
      "licenseDeclared": "NOASSERTION",
      "copyrightText": "NOASSERTION",
      "versionInfo": "v0.0.0-20190717185122-a985d3407aa7",
      "externalRefs": [
        {
          "referenceCategory": "PACKAGE-MANAGER",
          "referenceType": "purl",
          "referenceLocator": "pkg:golang/golang.org/x/xerrors@h1:I/5z698sn9Ka8TeJc9MKroUUfqBBauWjQqLJ2OPfmY0="
        }
      ],
      "supplier": "NOASSERTION"
    },
    {
      "name": "golang.org/x/sync",
      "SPDXID": "SPDXRef-Package-51B56F5C09F5DB6C5F245A31068CD765872343B3D605D2D03755C248CC4065F8",
      "downloadLocation": "NOASSERTION",
      "filesAnalyzed": false,
      "licenseConcluded": "NOASSERTION",
      "licenseDeclared": "NOASSERTION",
      "copyrightText": "NOASSERTION",
      "versionInfo": "v0.0.0-20201020160332-67f06af15bc9",
      "externalRefs": [
        {
          "referenceCategory": "PACKAGE-MANAGER",
          "referenceType": "purl",
          "referenceLocator": "pkg:golang/golang.org/x/sync@h1:RxMgew5VJxzue5/jJTE5uejpjVlOe/izrB70Jof72aM="
        }
      ],
      "supplier": "NOASSERTION"
    },
    {
      "name": "golang.org/x/mod",
      "SPDXID": "SPDXRef-Package-B381D93D92547360B20C4C6AE5A15CFDD41E01FCCFAE8A02AFA10BB59F9AB587",
      "downloadLocation": "NOASSERTION",
      "filesAnalyzed": false,
      "licenseConcluded": "NOASSERTION",
      "licenseDeclared": "NOASSERTION",
      "copyrightText": "NOASSERTION",
      "versionInfo": "v0.2.0",
      "externalRefs": [
        {
          "referenceCategory": "PACKAGE-MANAGER",
          "referenceType": "purl",
          "referenceLocator": "pkg:golang/golang.org/x/mod@h1:s0Qsj1ACt9ePp/hMypM3fl4fZqREWJwdYDEqhRiZZUA="
        }
      ],
      "supplier": "NOASSERTION"
    },
    {
      "name": "github.com/kr/text",
      "SPDXID": "SPDXRef-Package-F643431A62DF7430BA4708F4092DF9469A0A79CF1EAA9FC792CDAC6E01FED841",
      "downloadLocation": "NOASSERTION",
      "filesAnalyzed": false,
      "licenseConcluded": "NOASSERTION",
      "licenseDeclared": "NOASSERTION",
      "copyrightText": "NOASSERTION",
      "versionInfo": "v0.1.0",
      "externalRefs": [
        {
          "referenceCategory": "PACKAGE-MANAGER",
          "referenceType": "purl",
          "referenceLocator": "pkg:golang/github.com/kr/text@h1:4Jbv+DJW3UT/LiOwJeYQe1efqtUx/iVham/4vfdArNI="
        }
      ],
      "supplier": "NOASSERTION"
    },
    {
      "name": "github.com/golang/protobuf",
      "SPDXID": "SPDXRef-Package-770716D2224BBCD4659D448361F9B264F37EFCA10074BE68F41665D0B6608FAB",
      "downloadLocation": "NOASSERTION",
      "filesAnalyzed": false,
      "licenseConcluded": "NOASSERTION",
      "licenseDeclared": "NOASSERTION",
      "copyrightText": "NOASSERTION",
      "versionInfo": "v1.5.4",
      "externalRefs": [
        {
          "referenceCategory": "PACKAGE-MANAGER",
          "referenceType": "purl",
          "referenceLocator": "pkg:golang/github.com/golang/protobuf@h1:i7eJL8qZTpSEXOPTxNKhASYpMn+8e5Q6AdndVa1dWek="
        }
      ],
      "supplier": "NOASSERTION"
    },
    {
      "name": "google.golang.org/protobuf",
      "SPDXID": "SPDXRef-Package-2074FF2AE4917519B008AA6EBC6A8FA84A55F44FB8845E15093A6C47BB0DE33F",
      "downloadLocation": "NOASSERTION",
      "filesAnalyzed": false,
      "licenseConcluded": "NOASSERTION",
      "licenseDeclared": "NOASSERTION",
      "copyrightText": "NOASSERTION",
      "versionInfo": "v1.33.0",
      "externalRefs": [
        {
          "referenceCategory": "PACKAGE-MANAGER",
          "referenceType": "purl",
          "referenceLocator": "pkg:golang/google.golang.org/protobuf@h1:uNO2rsAINq/JlFpSdYEKIZ0uKD/R9cpdv0T+yoGwGmI="
        }
      ],
      "supplier": "NOASSERTION"
    },
    {
      "name": "github.com/kr/pretty",
      "SPDXID": "SPDXRef-Package-C993CD5D4E60396D8509E6F94C4E05744B913787CE753D67D36BE21B2BE5E55B",
      "downloadLocation": "NOASSERTION",
      "filesAnalyzed": false,
      "licenseConcluded": "NOASSERTION",
      "licenseDeclared": "NOASSERTION",
      "copyrightText": "NOASSERTION",
      "versionInfo": "v0.2.1",
      "externalRefs": [
        {
          "referenceCategory": "PACKAGE-MANAGER",
          "referenceType": "purl",
          "referenceLocator": "pkg:golang/github.com/kr/pretty@h1:ipq/a2n7PKx3OHsz4KJII5eveXtPO4qwEXGdVfWzfnI="
        }
      ],
      "supplier": "NOASSERTION"
    },
    {
      "name": "golang.org/x/crypto",
      "SPDXID": "SPDXRef-Package-E2ABBEF4D19026E4AC818A83BB15586D4ABFE941FB75419716A2C9E4ABFAD230",
      "downloadLocation": "NOASSERTION",
      "filesAnalyzed": false,
      "licenseConcluded": "NOASSERTION",
      "licenseDeclared": "NOASSERTION",
      "copyrightText": "NOASSERTION",
      "versionInfo": "v0.0.0-20191011191535-87dc89f01550",
      "externalRefs": [
        {
          "referenceCategory": "PACKAGE-MANAGER",
          "referenceType": "purl",
          "referenceLocator": "pkg:golang/golang.org/x/crypto@h1:yigFU9vqHzYiE8UmvKecakEJjdnWj3jj499lnFckfCI="
        }
      ],
      "supplier": "NOASSERTION"
    },
    {
      "name": "github.com/json-iterator/go",
      "SPDXID": "SPDXRef-Package-5430C9C15B152CF4564D01458E6A2C601AA0099821F40CCD3CD97EFB8347A6D6",
      "downloadLocation": "NOASSERTION",
      "filesAnalyzed": false,
      "licenseConcluded": "NOASSERTION",
      "licenseDeclared": "NOASSERTION",
      "copyrightText": "NOASSERTION",
      "versionInfo": "v1.1.12",
      "externalRefs": [
        {
          "referenceCategory": "PACKAGE-MANAGER",
          "referenceType": "purl",
          "referenceLocator": "pkg:golang/github.com/json-iterator/go@h1:PV8peI4a0ysnczrg+LtxykD8LfKY9ML6u2jnxaEnrnM="
        }
      ],
      "supplier": "NOASSERTION"
    },
    {
      "name": "golang.org/x/crypto",
      "SPDXID": "SPDXRef-Package-13A0F12D6762774B8734415858796EB317A828A8CCAE45B6445B4826231683D0",
      "downloadLocation": "NOASSERTION",
      "filesAnalyzed": false,
      "licenseConcluded": "NOASSERTION",
      "licenseDeclared": "NOASSERTION",
      "copyrightText": "NOASSERTION",
      "versionInfo": "v0.0.0-20190308221718-c2843e01d9a2",
      "externalRefs": [
        {
          "referenceCategory": "PACKAGE-MANAGER",
          "referenceType": "purl",
          "referenceLocator": "pkg:golang/golang.org/x/crypto@h1:djNgcEr1/C05ACkg1iLfiJU5Ep61QUkGW8qpdssI0+w="
        }
      ],
      "supplier": "NOASSERTION"
    },
    {
      "name": "github.com/modern-go/concurrent",
      "SPDXID": "SPDXRef-Package-601B14C50D96DF5831A949A3F602DE5E9253B66F98A6B3F08CA45862044F2F91",
      "downloadLocation": "NOASSERTION",
      "filesAnalyzed": false,
      "licenseConcluded": "NOASSERTION",
      "licenseDeclared": "NOASSERTION",
      "copyrightText": "NOASSERTION",
      "versionInfo": "v0.0.0-20180228061459-e0a39a4cb421",
      "externalRefs": [
        {
          "referenceCategory": "PACKAGE-MANAGER",
          "referenceType": "purl",
          "referenceLocator": "pkg:golang/github.com/modern-go/concurrent@h1:6dJC0mAP4ikYIbvyc7fijjWJddQyLn8Ig3JB5CqoB9Q="
        }
      ],
      "supplier": "NOASSERTION"
    },
    {
      "name": "github.com/stretchr/objx",
      "SPDXID": "SPDXRef-Package-3BF66000678C450DECC5923207ED2D7A836100994D89B829CE6E36757B074D4D",
      "downloadLocation": "NOASSERTION",
      "filesAnalyzed": false,
      "licenseConcluded": "NOASSERTION",
      "licenseDeclared": "NOASSERTION",
      "copyrightText": "NOASSERTION",
      "versionInfo": "v0.1.0",
      "externalRefs": [
        {
          "referenceCategory": "PACKAGE-MANAGER",
          "referenceType": "purl",
          "referenceLocator": "pkg:golang/github.com/stretchr/objx@h1:HFkY916IF+rwdDfMAkV7OtwuqBVzrE8GR6GFx+wExME="
        }
      ],
      "supplier": "NOASSERTION"
    },
    {
      "name": "github.com/davecgh/go-spew",
      "SPDXID": "SPDXRef-Package-4A5348D7EAD57322A56631311BB791C7B9BB5EC105E5D82CC189CA3EB9A2DA97",
      "downloadLocation": "NOASSERTION",
      "filesAnalyzed": false,
      "licenseConcluded": "NOASSERTION",
      "licenseDeclared": "NOASSERTION",
      "copyrightText": "NOASSERTION",
      "versionInfo": "v1.1.0",
      "externalRefs": [
        {
          "referenceCategory": "PACKAGE-MANAGER",
          "referenceType": "purl",
          "referenceLocator": "pkg:golang/github.com/davecgh/go-spew@h1:J7Y8YcW2NihsgmVo/mv3lAwl/skON4iLHjSsI+c5H38="
        }
      ],
      "supplier": "NOASSERTION"
    },
    {
      "name": "k8s.io/klog/v2",
      "SPDXID": "SPDXRef-Package-383A474A54A0F57D652E2CDA0934E113F3DD9B88BB0A8C9142D0BD377D141D32",
      "downloadLocation": "NOASSERTION",
      "filesAnalyzed": false,
      "licenseConcluded": "NOASSERTION",
      "licenseDeclared": "NOASSERTION",
      "copyrightText": "NOASSERTION",
      "versionInfo": "v2.120.1",
      "externalRefs": [
        {
          "referenceCategory": "PACKAGE-MANAGER",
          "referenceType": "purl",
          "referenceLocator": "pkg:golang/k8s.io/klog/v2@h1:QXU6cPEOIslTGvZaXvFWiP9VKyeet3sawzTOvdXb4Vw="
        }
      ],
      "supplier": "NOASSERTION"
    },
    {
      "name": "gopkg.in/yaml.v3",
      "SPDXID": "SPDXRef-Package-C789728058FB6A65C5B8CC48C180C7AB809F66D1B9CC529856294FC6FEA74054",
      "downloadLocation": "NOASSERTION",
      "filesAnalyzed": false,
      "licenseConcluded": "NOASSERTION",
      "licenseDeclared": "NOASSERTION",
      "copyrightText": "NOASSERTION",
      "versionInfo": "v3.0.1",
      "externalRefs": [
        {
          "referenceCategory": "PACKAGE-MANAGER",
          "referenceType": "purl",
          "referenceLocator": "pkg:golang/gopkg.in/yaml.v3@h1:fxVm/GzAzEWqLHuvctI91KS9hhNmmWOoWu0XTYJS7CA="
        }
      ],
      "supplier": "NOASSERTION"
    },
    {
      "name": "github.com/google/gofuzz",
      "SPDXID": "SPDXRef-Package-36AC1803C583BCDC688F83419CA5509CA3BBB2E134B031F0D59CF5270A5C2F09",
      "downloadLocation": "NOASSERTION",
      "filesAnalyzed": false,
      "licenseConcluded": "NOASSERTION",
      "licenseDeclared": "NOASSERTION",
      "copyrightText": "NOASSERTION",
      "versionInfo": "v1.0.0",
      "externalRefs": [
        {
          "referenceCategory": "PACKAGE-MANAGER",
          "referenceType": "purl",
          "referenceLocator": "pkg:golang/github.com/google/gofuzz@h1:dBl0BpW6vV/+mYPU4Po3pmUjxk6FQPldtuIdl/M65Eg="
        }
      ],
      "supplier": "NOASSERTION"
    },
    {
      "name": "golang.org/x/net",
      "SPDXID": "SPDXRef-Package-2C210F1EC0B25582C773EE8E0EFD3AF282CE522FA5A71968C5790F5F3A921B43",
      "downloadLocation": "NOASSERTION",
      "filesAnalyzed": false,
      "licenseConcluded": "NOASSERTION",
      "licenseDeclared": "NOASSERTION",
      "copyrightText": "NOASSERTION",
      "versionInfo": "v0.23.0",
      "externalRefs": [
        {
          "referenceCategory": "PACKAGE-MANAGER",
          "referenceType": "purl",
          "referenceLocator": "pkg:golang/golang.org/x/net@h1:7EYJ93RZ9vYSZAIb2x3lnuvqO5zneoD6IvWjuhfxjTs="
        }
      ],
      "supplier": "NOASSERTION"
    },
    {
      "name": "github.com/stretchr/testify",
      "SPDXID": "SPDXRef-Package-1B6E1C2ACE25D47A11940D47BD4713978F8102238AE51B61A52A7EF2301D784B",
      "downloadLocation": "NOASSERTION",
      "filesAnalyzed": false,
      "licenseConcluded": "NOASSERTION",
      "licenseDeclared": "NOASSERTION",
      "copyrightText": "NOASSERTION",
      "versionInfo": "v1.8.4",
      "externalRefs": [
        {
          "referenceCategory": "PACKAGE-MANAGER",
          "referenceType": "purl",
          "referenceLocator": "pkg:golang/github.com/stretchr/testify@h1:CcVxjf3Q8PM0mHUKJCdn+eZZtm5yQwehR5yeSVQQcUk="
        }
      ],
      "supplier": "NOASSERTION"
    },
    {
      "name": "golang.org/x/text",
      "SPDXID": "SPDXRef-Package-02BDF6AE45C73E44F28C826A9589F1BA3D6380975FED32E2F332543E21502AFC",
      "downloadLocation": "NOASSERTION",
      "filesAnalyzed": false,
      "licenseConcluded": "NOASSERTION",
      "licenseDeclared": "NOASSERTION",
      "copyrightText": "NOASSERTION",
      "versionInfo": "v0.14.0",
      "externalRefs": [
        {
          "referenceCategory": "PACKAGE-MANAGER",
          "referenceType": "purl",
          "referenceLocator": "pkg:golang/golang.org/x/text@h1:ScX5w1eTa3QqT8oi6+ziP7dTV1S2+ALU0bI+0zXKWiQ="
        }
      ],
      "supplier": "NOASSERTION"
    },
    {
      "name": "golang.org/x/xerrors",
      "SPDXID": "SPDXRef-Package-177BFE1A91780FDE779F74A5D45D6B2E30FABB027D42CFFDCF24549F7D394765",
      "downloadLocation": "NOASSERTION",
      "filesAnalyzed": false,
      "licenseConcluded": "NOASSERTION",
      "licenseDeclared": "NOASSERTION",
      "copyrightText": "NOASSERTION",
      "versionInfo": "v0.0.0-20191011141410-1b5146add898",
      "externalRefs": [
        {
          "referenceCategory": "PACKAGE-MANAGER",
          "referenceType": "purl",
          "referenceLocator": "pkg:golang/golang.org/x/xerrors@h1:I/5z698sn9Ka8TeJc9MKroUUfqBBauWjQqLJ2OPfmY0="
        }
      ],
      "supplier": "NOASSERTION"
    },
    {
      "name": "golang.org/x/tools",
      "SPDXID": "SPDXRef-Package-EA8DC12E44139D9AC7AD2720FF84433B3E1A0376C441D8D9531FB1942F1DCF57",
      "downloadLocation": "NOASSERTION",
      "filesAnalyzed": false,
      "licenseConcluded": "NOASSERTION",
      "licenseDeclared": "NOASSERTION",
      "copyrightText": "NOASSERTION",
      "versionInfo": "v0.0.0-20210106214847-113979e3529a",
      "externalRefs": [
        {
          "referenceCategory": "PACKAGE-MANAGER",
          "referenceType": "purl",
          "referenceLocator": "pkg:golang/golang.org/x/tools@h1:emZCQorbCU4vsT4fOWvOPXz4eW1wZW4PmDk9uLelYpA="
        }
      ],
      "supplier": "NOASSERTION"
    },
    {
      "name": "github.com/modern-go/concurrent",
      "SPDXID": "SPDXRef-Package-5C2D87CEF5257E39ECDCF36FFC7EEFC06F3281D2B8B1DC3EE116F6DEC4E44E21",
      "downloadLocation": "NOASSERTION",
      "filesAnalyzed": false,
      "licenseConcluded": "NOASSERTION",
      "licenseDeclared": "NOASSERTION",
      "copyrightText": "NOASSERTION",
      "versionInfo": "v0.0.0-20180306012644-bacd9c7ef1dd",
      "externalRefs": [
        {
          "referenceCategory": "PACKAGE-MANAGER",
          "referenceType": "purl",
          "referenceLocator": "pkg:golang/github.com/modern-go/concurrent@h1:TRLaZ9cD/w8PVh93nsPXa1VrQ6jlwL5oN8l14QlcNfg="
        }
      ],
      "supplier": "NOASSERTION"
    },
    {
      "name": "k8s.io/apimachinery",
      "SPDXID": "SPDXRef-Package-D3216033B89098B889E6A5B95BF6D450EE50C951805B15CE7BC87F828DDD0874",
      "downloadLocation": "NOASSERTION",
      "filesAnalyzed": false,
      "licenseConcluded": "NOASSERTION",
      "licenseDeclared": "NOASSERTION",
      "copyrightText": "NOASSERTION",
      "versionInfo": "v0.30.1",
      "externalRefs": [
        {
          "referenceCategory": "PACKAGE-MANAGER",
          "referenceType": "purl",
          "referenceLocator": "pkg:golang/k8s.io/apimachinery@h1:ZQStsEfo4n65yAdlGTfP/uSHMQSoYzU/oeEbkmF7P2U="
        }
      ],
      "supplier": "NOASSERTION"
    },
    {
      "name": "k8s.io/utils",
      "SPDXID": "SPDXRef-Package-95F91413D681E88A5A238D8AABB681D58A535AED22A368F757C009930FB6E38F",
      "downloadLocation": "NOASSERTION",
      "filesAnalyzed": false,
      "licenseConcluded": "NOASSERTION",
      "licenseDeclared": "NOASSERTION",
      "copyrightText": "NOASSERTION",
      "versionInfo": "v0.0.0-20230726121419-3b25d923346b",
      "externalRefs": [
        {
          "referenceCategory": "PACKAGE-MANAGER",
          "referenceType": "purl",
          "referenceLocator": "pkg:golang/k8s.io/utils@h1:sgn3ZU783SCgtaSJjpcVVlRqd6GSnlTLKgpAAttJvpI="
        }
      ],
      "supplier": "NOASSERTION"
    },
    {
      "name": "gopkg.in/yaml.v2",
      "SPDXID": "SPDXRef-Package-52135839EA35478FEC48ADC4A6664FC7EE10B96DB2FFFF336D14AF10C6CE7439",
      "downloadLocation": "NOASSERTION",
      "filesAnalyzed": false,
      "licenseConcluded": "NOASSERTION",
      "licenseDeclared": "NOASSERTION",
      "copyrightText": "NOASSERTION",
      "versionInfo": "v2.2.8",
      "externalRefs": [
        {
          "referenceCategory": "PACKAGE-MANAGER",
          "referenceType": "purl",
          "referenceLocator": "pkg:golang/gopkg.in/yaml.v2@h1:hI93XBmqTisBFMUTm0b8Fm+jr3Dg1NNxqwp+5A1VGuI="
        }
      ],
      "supplier": "NOASSERTION"
    },
    {
      "name": "github.com/google/gofuzz",
      "SPDXID": "SPDXRef-Package-265650581814BCFA8E073975CD6CF38EE37FD498235C00821F158F181BE249AB",
      "downloadLocation": "NOASSERTION",
      "filesAnalyzed": false,
      "licenseConcluded": "NOASSERTION",
      "licenseDeclared": "NOASSERTION",
      "copyrightText": "NOASSERTION",
      "versionInfo": "v1.2.0",
      "externalRefs": [
        {
          "referenceCategory": "PACKAGE-MANAGER",
          "referenceType": "purl",
          "referenceLocator": "pkg:golang/github.com/google/gofuzz@h1:xRy4A+RhZaiKjJ1bPfwQ8sedCA+YS2YcCHW6ec7JMi0="
        }
      ],
      "supplier": "NOASSERTION"
    },
    {
      "name": "golang.org/x/sys",
      "SPDXID": "SPDXRef-Package-EDACF26B8AC1A6E7B01AD38693C0939218D98361EAB3F61A94129C51F79B2D18",
      "downloadLocation": "NOASSERTION",
      "filesAnalyzed": false,
      "licenseConcluded": "NOASSERTION",
      "licenseDeclared": "NOASSERTION",
      "copyrightText": "NOASSERTION",
      "versionInfo": "v0.0.0-20200930185726-fdedc70b468f",
      "externalRefs": [
        {
          "referenceCategory": "PACKAGE-MANAGER",
          "referenceType": "purl",
          "referenceLocator": "pkg:golang/golang.org/x/sys@h1:h1NjWce9XRLGQEsW7wpKNCjG9DtNlClVuFLEZdDNbEs="
        }
      ],
      "supplier": "NOASSERTION"
    },
    {
      "name": "golang.org/x/text",
      "SPDXID": "SPDXRef-Package-970D97175DC9F5271B204F15F2803F46CD516DA8DCD46A53C1DA939702ED19FB",
      "downloadLocation": "NOASSERTION",
      "filesAnalyzed": false,
      "licenseConcluded": "NOASSERTION",
      "licenseDeclared": "NOASSERTION",
      "copyrightText": "NOASSERTION",
      "versionInfo": "v0.3.0",
      "externalRefs": [
        {
          "referenceCategory": "PACKAGE-MANAGER",
          "referenceType": "purl",
          "referenceLocator": "pkg:golang/golang.org/x/text@h1:NqM8EUOU14njkJ3fqMW+pc6Ldnwhi/IjpwHt7yyuwOQ="
        }
      ],
      "supplier": "NOASSERTION"
    },
    {
      "name": "github.com/stretchr/testify",
      "SPDXID": "SPDXRef-Package-FA7E8A9DA905CF941B611ED89146A7796BCD28B3E602E4280922ADB1233A053E",
      "downloadLocation": "NOASSERTION",
      "filesAnalyzed": false,
      "licenseConcluded": "NOASSERTION",
      "licenseDeclared": "NOASSERTION",
      "copyrightText": "NOASSERTION",
      "versionInfo": "v1.3.0",
      "externalRefs": [
        {
          "referenceCategory": "PACKAGE-MANAGER",
          "referenceType": "purl",
          "referenceLocator": "pkg:golang/github.com/stretchr/testify@h1:M5WIy9Dh21IEIfnGCwXGc5bZfKNJtfHm1UVUgZn+9EI="
        }
      ],
      "supplier": "NOASSERTION"
    },
    {
      "name": "github.com/google/go-cmp",
      "SPDXID": "SPDXRef-Package-E41120416AE198ED43DEDF4B7261349A2361E7AFA97EF854D8A3A32C09E324F8",
      "downloadLocation": "NOASSERTION",
      "filesAnalyzed": false,
      "licenseConcluded": "NOASSERTION",
      "licenseDeclared": "NOASSERTION",
      "copyrightText": "NOASSERTION",
      "versionInfo": "v0.6.0",
      "externalRefs": [
        {
          "referenceCategory": "PACKAGE-MANAGER",
          "referenceType": "purl",
          "referenceLocator": "pkg:golang/github.com/google/go-cmp@h1:ofyhxvXcZhMsU5ulbFiLKl/XBFqE1GSq7atu8tAmTRI="
        }
      ],
      "supplier": "NOASSERTION"
    },
    {
      "name": "github.com/rogpeppe/go-internal",
      "SPDXID": "SPDXRef-Package-A484D358DF8630A9E8CA5228C8EF114F4B75296BE494FE97A3E5CC25F997E031",
      "downloadLocation": "NOASSERTION",
      "filesAnalyzed": false,
      "licenseConcluded": "NOASSERTION",
      "licenseDeclared": "NOASSERTION",
      "copyrightText": "NOASSERTION",
      "versionInfo": "v1.10.0",
      "externalRefs": [
        {
          "referenceCategory": "PACKAGE-MANAGER",
          "referenceType": "purl",
          "referenceLocator": "pkg:golang/github.com/rogpeppe/go-internal@h1:TMyTOH3F/DB16zRVcYyreMH6GnZZrwQVAoYjRBZyWFQ="
        }
      ],
      "supplier": "NOASSERTION"
    },
    {
      "name": "github.com/pmezard/go-difflib",
      "SPDXID": "SPDXRef-Package-EC569588B44E6DEF64FD5ABB8107D03E0ABA38AEC9068177157EE6F2464753E1",
      "downloadLocation": "NOASSERTION",
      "filesAnalyzed": false,
      "licenseConcluded": "NOASSERTION",
      "licenseDeclared": "NOASSERTION",
      "copyrightText": "NOASSERTION",
      "versionInfo": "v1.0.0",
      "externalRefs": [
        {
          "referenceCategory": "PACKAGE-MANAGER",
          "referenceType": "purl",
          "referenceLocator": "pkg:golang/github.com/pmezard/go-difflib@h1:4DBwDE0NGyQoBHbLQYPwSUPoCMWR5BEzIk/f1lZbAQM="
        }
      ],
      "supplier": "NOASSERTION"
    },
    {
      "name": "golang.org/x/sync",
      "SPDXID": "SPDXRef-Package-71EB876CFB97EA5AF67046ECA53B3B62ECED15E581E9899721A45E81C904B7B4",
      "downloadLocation": "NOASSERTION",
      "filesAnalyzed": false,
      "licenseConcluded": "NOASSERTION",
      "licenseDeclared": "NOASSERTION",
      "copyrightText": "NOASSERTION",
      "versionInfo": "v0.0.0-20190423024810-112230192c58",
      "externalRefs": [
        {
          "referenceCategory": "PACKAGE-MANAGER",
          "referenceType": "purl",
          "referenceLocator": "pkg:golang/golang.org/x/sync@h1:RxMgew5VJxzue5/jJTE5uejpjVlOe/izrB70Jof72aM="
        }
      ],
      "supplier": "NOASSERTION"
    },
    {
      "name": "github.com/modern-go/reflect2",
      "SPDXID": "SPDXRef-Package-65225ED5EB2C24AE796645ED3E67C3BE7C4A1527579A6EB1CC72044B05139627",
      "downloadLocation": "NOASSERTION",
      "filesAnalyzed": false,
      "licenseConcluded": "NOASSERTION",
      "licenseDeclared": "NOASSERTION",
      "copyrightText": "NOASSERTION",
      "versionInfo": "v1.0.2",
      "externalRefs": [
        {
          "referenceCategory": "PACKAGE-MANAGER",
          "referenceType": "purl",
          "referenceLocator": "pkg:golang/github.com/modern-go/reflect2@h1:xBagoLtFs94CBntxluKeaWgTMpvLxC4ur3nMaC9Gz0M="
        }
      ],
      "supplier": "NOASSERTION"
    },
    {
      "name": "github.com/yuin/goldmark",
      "SPDXID": "SPDXRef-Package-18ABA61FD625D3F690D268508DD7171D960D6A34CAD12E94D35EC8504026AC7F",
      "downloadLocation": "NOASSERTION",
      "filesAnalyzed": false,
      "licenseConcluded": "NOASSERTION",
      "licenseDeclared": "NOASSERTION",
      "copyrightText": "NOASSERTION",
      "versionInfo": "v1.1.27",
      "externalRefs": [
        {
          "referenceCategory": "PACKAGE-MANAGER",
          "referenceType": "purl",
          "referenceLocator": "pkg:golang/github.com/yuin/goldmark@h1:3hX8gzYuyVAZsxl0MRgGTJEmQBFcNTphYh9decYSb74="
        }
      ],
      "supplier": "NOASSERTION"
    },
    {
      "name": "github.com/kr/pty",
      "SPDXID": "SPDXRef-Package-C6E932756A9242C20A3191625E752B03AF0915B2DC02F3C1DFDB6E9E88F89399",
      "downloadLocation": "NOASSERTION",
      "filesAnalyzed": false,
      "licenseConcluded": "NOASSERTION",
      "licenseDeclared": "NOASSERTION",
      "copyrightText": "NOASSERTION",
      "versionInfo": "v1.1.1",
      "externalRefs": [
        {
          "referenceCategory": "PACKAGE-MANAGER",
          "referenceType": "purl",
          "referenceLocator": "pkg:golang/github.com/kr/pty@h1:pFQYn66WHrOpPYNljwOMqo10TkYh1fy3cYio2l3bCsQ="
        }
      ],
      "supplier": "NOASSERTION"
    },
    {
      "name": "golang.org/x/net",
      "SPDXID": "SPDXRef-Package-84214E65517E87BEFAC8A979E530703D5E066716352F5947FCF4EBE293AB85CF",
      "downloadLocation": "NOASSERTION",
      "filesAnalyzed": false,
      "licenseConcluded": "NOASSERTION",
      "licenseDeclared": "NOASSERTION",
      "copyrightText": "NOASSERTION",
      "versionInfo": "v0.0.0-20190404232315-eb5bcb51f2a3",
      "externalRefs": [
        {
          "referenceCategory": "PACKAGE-MANAGER",
          "referenceType": "purl",
          "referenceLocator": "pkg:golang/golang.org/x/net@h1:t9HGtf8HONx5eT2rtn7q6eTqICYqUVnKs3thJo3Qplg="
        }
      ],
      "supplier": "NOASSERTION"
    },
    {
      "name": "golang.org/x/tools",
      "SPDXID": "SPDXRef-Package-7FDEE8E8B947E81084A6A61E4532D4B3AFBB41C9B08E152D811CA14344AFBE01",
      "downloadLocation": "NOASSERTION",
      "filesAnalyzed": false,
      "licenseConcluded": "NOASSERTION",
      "licenseDeclared": "NOASSERTION",
      "copyrightText": "NOASSERTION",
      "versionInfo": "v0.0.0-20180917221912-90fa682c2a6e",
      "externalRefs": [
        {
          "referenceCategory": "PACKAGE-MANAGER",
          "referenceType": "purl",
          "referenceLocator": "pkg:golang/golang.org/x/tools@h1:n7NCudcB/nEzxVGmLbDWY5pfWTLqBcC2KZ6jyYvM4mQ="
        }
      ],
      "supplier": "NOASSERTION"
    },
    {
      "name": "github.com/go-logr/logr",
      "SPDXID": "SPDXRef-Package-38B02901A4E91407BF8F822BB760A85D2FC784EF5C91FB60C38FB78206745093",
      "downloadLocation": "NOASSERTION",
      "filesAnalyzed": false,
      "licenseConcluded": "NOASSERTION",
      "licenseDeclared": "NOASSERTION",
      "copyrightText": "NOASSERTION",
      "versionInfo": "v1.4.1",
      "externalRefs": [
        {
          "referenceCategory": "PACKAGE-MANAGER",
          "referenceType": "purl",
          "referenceLocator": "pkg:golang/github.com/go-logr/logr@h1:pKouT5E8xu9zeFC39JXRDukb6JFQPXM5p5I91188VAQ="
        }
      ],
      "supplier": "NOASSERTION"
    },
    {
      "name": "golang.org/x/text",
      "SPDXID": "SPDXRef-Package-212255077A0F752D4251E972D4A69A2AFB9488C0A77DD6F9A66A65C2F78F58F8",
      "downloadLocation": "NOASSERTION",
      "filesAnalyzed": false,
      "licenseConcluded": "NOASSERTION",
      "licenseDeclared": "NOASSERTION",
      "copyrightText": "NOASSERTION",
      "versionInfo": "v0.3.3",
      "externalRefs": [
        {
          "referenceCategory": "PACKAGE-MANAGER",
          "referenceType": "purl",
          "referenceLocator": "pkg:golang/golang.org/x/text@h1:5Zoc/QRtKVWzQhOtBMvqHzDpF6irO9z98xDceosuGiQ="
        }
      ],
      "supplier": "NOASSERTION"
    },
    {
      "name": "golang.org/x/mod",
      "SPDXID": "SPDXRef-Package-420C98B9E896762E707F2B9415FE879958DB14C4FD4A11F466D61250CD4356E7",
      "downloadLocation": "NOASSERTION",
      "filesAnalyzed": false,
      "licenseConcluded": "NOASSERTION",
      "licenseDeclared": "NOASSERTION",
      "copyrightText": "NOASSERTION",
      "versionInfo": "v0.3.0",
      "externalRefs": [
        {
          "referenceCategory": "PACKAGE-MANAGER",
          "referenceType": "purl",
          "referenceLocator": "pkg:golang/golang.org/x/mod@h1:s0Qsj1ACt9ePp/hMypM3fl4fZqREWJwdYDEqhRiZZUA="
        }
      ],
      "supplier": "NOASSERTION"
    },
    {
      "name": "github.com/davecgh/go-spew",
      "SPDXID": "SPDXRef-Package-AF8E58564B82E13CA0207F61028BBC26AC45AFED76D355764166AD9564C2197F",
      "downloadLocation": "NOASSERTION",
      "filesAnalyzed": false,
      "licenseConcluded": "NOASSERTION",
      "licenseDeclared": "NOASSERTION",
      "copyrightText": "NOASSERTION",
      "versionInfo": "v1.1.1",
      "externalRefs": [
        {
          "referenceCategory": "PACKAGE-MANAGER",
          "referenceType": "purl",
          "referenceLocator": "pkg:golang/github.com/davecgh/go-spew@h1:vj9j/u1bqnvCEfJOwUhtlOARqs3+rkHYY13jYWTU97c="
        }
      ],
      "supplier": "NOASSERTION"
    },
    {
      "name": "gopkg.in/yaml.v2",
      "SPDXID": "SPDXRef-Package-35288EC2044BA02271D28C93E07A11A14C07C3171BC7F82DAD8380D2B88EE690",
      "downloadLocation": "NOASSERTION",
      "filesAnalyzed": false,
      "licenseConcluded": "NOASSERTION",
      "licenseDeclared": "NOASSERTION",
      "copyrightText": "NOASSERTION",
      "versionInfo": "v2.4.0",
      "externalRefs": [
        {
          "referenceCategory": "PACKAGE-MANAGER",
          "referenceType": "purl",
          "referenceLocator": "pkg:golang/gopkg.in/yaml.v2@h1:D8xgwECY7CYvx+Y2n4sBz93Jn9JRvxdiyyo8CTfuKaY="
        }
      ],
      "supplier": "NOASSERTION"
    },
    {
      "name": "github.com/kr/pretty",
      "SPDXID": "SPDXRef-Package-69CEF2FBDBCDDACA6D718F6DF351C94D394604E3FAC4AF555207490B8C60F265",
      "downloadLocation": "NOASSERTION",
      "filesAnalyzed": false,
      "licenseConcluded": "NOASSERTION",
      "licenseDeclared": "NOASSERTION",
      "copyrightText": "NOASSERTION",
      "versionInfo": "v0.3.1",
      "externalRefs": [
        {
          "referenceCategory": "PACKAGE-MANAGER",
          "referenceType": "purl",
          "referenceLocator": "pkg:golang/github.com/kr/pretty@h1:flRD4NNwYAUpkphVc1HcthR4KEIFJ65n8Mw5qdRn3LE="
        }
      ],
      "supplier": "NOASSERTION"
    },
    {
      "name": "golang.org/x/tools",
      "SPDXID": "SPDXRef-Package-E72FE5EB82C2581D4FF7C7136B5703454E56EE69293860B10817C948D14A56E4",
      "downloadLocation": "NOASSERTION",
      "filesAnalyzed": false,
      "licenseConcluded": "NOASSERTION",
      "licenseDeclared": "NOASSERTION",
      "copyrightText": "NOASSERTION",
      "versionInfo": "v0.0.0-20191119224855-298f0cb1881e",
      "externalRefs": [
        {
          "referenceCategory": "PACKAGE-MANAGER",
          "referenceType": "purl",
          "referenceLocator": "pkg:golang/golang.org/x/tools@h1:b+2E5dAYhXwXZwtnZ6UAqBI28+e2cm9otk0dWdXHAEo="
        }
      ],
      "supplier": "NOASSERTION"
    },
    {
      "name": "golang.org/x/net",
      "SPDXID": "SPDXRef-Package-A7E9F216CBCA8DCDD8D155798D23F0C80B0D9F5C988BD006E2155EF2493F69E9",
      "downloadLocation": "NOASSERTION",
      "filesAnalyzed": false,
      "licenseConcluded": "NOASSERTION",
      "licenseDeclared": "NOASSERTION",
      "copyrightText": "NOASSERTION",
      "versionInfo": "v0.0.0-20201021035429-f5854403a974",
      "externalRefs": [
        {
          "referenceCategory": "PACKAGE-MANAGER",
          "referenceType": "purl",
          "referenceLocator": "pkg:golang/golang.org/x/net@h1:sp8m0HH+o8qH0wwXwYZr8TS3Oi6o0r6Gce1SSxlDquU="
        }
      ],
      "supplier": "NOASSERTION"
    },
    {
      "name": "golang.org/x/sys",
      "SPDXID": "SPDXRef-Package-8446DC2D4DCE972685FA381430FB2C7E28E48031C44055FF8461D0F681A55375",
      "downloadLocation": "NOASSERTION",
      "filesAnalyzed": false,
      "licenseConcluded": "NOASSERTION",
      "licenseDeclared": "NOASSERTION",
      "copyrightText": "NOASSERTION",
      "versionInfo": "v0.0.0-20190412213103-97732733099d",
      "externalRefs": [
        {
          "referenceCategory": "PACKAGE-MANAGER",
          "referenceType": "purl",
          "referenceLocator": "pkg:golang/golang.org/x/sys@h1:h1NjWce9XRLGQEsW7wpKNCjG9DtNlClVuFLEZdDNbEs="
        }
      ],
      "supplier": "NOASSERTION"
    },
    {
      "name": "golang.org/x/xerrors",
      "SPDXID": "SPDXRef-Package-48B79D5F6FFF98C09DEA83114649014217A3858A32B82AF3FBB9395395A29B7D",
      "downloadLocation": "NOASSERTION",
      "filesAnalyzed": false,
      "licenseConcluded": "NOASSERTION",
      "licenseDeclared": "NOASSERTION",
      "copyrightText": "NOASSERTION",
      "versionInfo": "v0.0.0-20200804184101-5ec99f83aff1",
      "externalRefs": [
        {
          "referenceCategory": "PACKAGE-MANAGER",
          "referenceType": "purl",
          "referenceLocator": "pkg:golang/golang.org/x/xerrors@h1:I/5z698sn9Ka8TeJc9MKroUUfqBBauWjQqLJ2OPfmY0="
        }
      ],
      "supplier": "NOASSERTION"
    },
    {
      "name": "github.com/yuin/goldmark",
      "SPDXID": "SPDXRef-Package-93414AC39BB04FFF7097542621AF10D94AA890E8BCB8619AD1C4FADD98FA4E57",
      "downloadLocation": "NOASSERTION",
      "filesAnalyzed": false,
      "licenseConcluded": "NOASSERTION",
      "licenseDeclared": "NOASSERTION",
      "copyrightText": "NOASSERTION",
      "versionInfo": "v1.2.1",
      "externalRefs": [
        {
          "referenceCategory": "PACKAGE-MANAGER",
          "referenceType": "purl",
          "referenceLocator": "pkg:golang/github.com/yuin/goldmark@h1:3hX8gzYuyVAZsxl0MRgGTJEmQBFcNTphYh9decYSb74="
        }
      ],
      "supplier": "NOASSERTION"
    },
    {
      "name": "gopkg.in/check.v1",
      "SPDXID": "SPDXRef-Package-3ED87A63167926B1AD760EEFD8B5F0F80EC92D1B8863633437D0E2B564F3306E",
      "downloadLocation": "NOASSERTION",
      "filesAnalyzed": false,
      "licenseConcluded": "NOASSERTION",
      "licenseDeclared": "NOASSERTION",
      "copyrightText": "NOASSERTION",
      "versionInfo": "v1.0.0-20201130134442-10cb98267c6c",
      "externalRefs": [
        {
          "referenceCategory": "PACKAGE-MANAGER",
          "referenceType": "purl",
          "referenceLocator": "pkg:golang/gopkg.in/check.v1@h1:Hei/4ADfdWqJk1ZMxUNpqntNwaWcugrBjAiHlqqRiVk="
        }
      ],
      "supplier": "NOASSERTION"
    },
    {
      "name": "golang.org/x/crypto",
      "SPDXID": "SPDXRef-Package-0442CBDB745F42024DDE6CFFE8C78F6B459D8E04E85C4F533C7342F68658B0AB",
      "downloadLocation": "NOASSERTION",
      "filesAnalyzed": false,
      "licenseConcluded": "NOASSERTION",
      "licenseDeclared": "NOASSERTION",
      "copyrightText": "NOASSERTION",
      "versionInfo": "v0.0.0-20200622213623-75b288015ac9",
      "externalRefs": [
        {
          "referenceCategory": "PACKAGE-MANAGER",
          "referenceType": "purl",
          "referenceLocator": "pkg:golang/golang.org/x/crypto@h1:LzIPMQfyMNhhGPhUkYOs5KpL4U8rLKemX1yGLhDgUto="
        }
      ],
      "supplier": "NOASSERTION"
    },
    {
      "name": "github.com/google/go-cmp",
      "SPDXID": "SPDXRef-Package-C73F0E93BB5784C56E48D3C923A4EE05EFB7687707BEBCBA3ADB4C64496882D6",
      "downloadLocation": "NOASSERTION",
      "filesAnalyzed": false,
      "licenseConcluded": "NOASSERTION",
      "licenseDeclared": "NOASSERTION",
      "copyrightText": "NOASSERTION",
      "versionInfo": "v0.5.9",
      "externalRefs": [
        {
          "referenceCategory": "PACKAGE-MANAGER",
          "referenceType": "purl",
          "referenceLocator": "pkg:golang/github.com/google/go-cmp@h1:17dUlkBOakJ0+DkrSSNjCkIjxS6bF9zb3elmeNGIjoY="
        }
      ],
      "supplier": "NOASSERTION"
    },
    {
      "name": "github.com/gogo/protobuf",
      "SPDXID": "SPDXRef-Package-FA429DD2BF710E5F4CCEA7319830D74469C28F0F5D114CFBB98394F33BC050B3",
      "downloadLocation": "NOASSERTION",
      "filesAnalyzed": false,
      "licenseConcluded": "NOASSERTION",
      "licenseDeclared": "NOASSERTION",
      "copyrightText": "NOASSERTION",
      "versionInfo": "v1.3.2",
      "externalRefs": [
        {
          "referenceCategory": "PACKAGE-MANAGER",
          "referenceType": "purl",
          "referenceLocator": "pkg:golang/github.com/gogo/protobuf@h1:Ov1cvc58UF3b5XjBnZv7+opcTcQFZebYjWzi34vdm4Q="
        }
      ],
      "supplier": "NOASSERTION"
    },
    {
      "name": "gopkg.in/check.v1",
      "SPDXID": "SPDXRef-Package-F6001A48857D236BA810FA40E43707182FAFEAF37F47274F8B520A6366563355",
      "downloadLocation": "NOASSERTION",
      "filesAnalyzed": false,
      "licenseConcluded": "NOASSERTION",
      "licenseDeclared": "NOASSERTION",
      "copyrightText": "NOASSERTION",
      "versionInfo": "v0.0.0-20161208181325-20d25e280405",
      "externalRefs": [
        {
          "referenceCategory": "PACKAGE-MANAGER",
          "referenceType": "purl",
          "referenceLocator": "pkg:golang/gopkg.in/check.v1@h1:Co6ibVJAznAaIkqp8huTwlJQCZ016jof/cbN4VW5Yz0="
        }
      ],
      "supplier": "NOASSERTION"
    },
    {
      "name": "api",
      "SPDXID": "SPDXRef-RootPackage",
      "downloadLocation": "NOASSERTION",
      "packageVerificationCode": {
        "packageVerificationCodeValue": "da39a3ee5e6b4b0d3255bfef95601890afd80709"
      },
      "filesAnalyzed": true,
      "licenseConcluded": "NOASSERTION",
      "licenseInfoFromFiles": [
        "NOASSERTION"
      ],
      "licenseDeclared": "NOASSERTION",
      "copyrightText": "NOASSERTION",
      "versionInfo": "v0.30.1",
      "externalRefs": [
        {
          "referenceCategory": "PACKAGE-MANAGER",
          "referenceType": "purl",
          "referenceLocator": "pkg:swid/wipro/github.com/api@v0.30.1?tag_id=10ecd4eb-343a-4aa4-b76d-a51c9301f77f"
        }
      ],
      "supplier": "Organization: wipro",
      "hasFiles": []
    }
  ],
  "externalDocumentRefs": [],
  "relationships": [
    {
      "relationshipType": "DESCRIBES",
      "relatedSpdxElement": "SPDXRef-RootPackage",
      "spdxElementId": "SPDXRef-DOCUMENT"
    },
    {
      "relationshipType": "DEPENDS_ON",
      "relatedSpdxElement": "SPDXRef-Package-F6001A48857D236BA810FA40E43707182FAFEAF37F47274F8B520A6366563355",
      "spdxElementId": "SPDXRef-RootPackage"
    },
    {
      "relationshipType": "DEPENDS_ON",
      "relatedSpdxElement": "SPDXRef-Package-FA429DD2BF710E5F4CCEA7319830D74469C28F0F5D114CFBB98394F33BC050B3",
      "spdxElementId": "SPDXRef-RootPackage"
    },
    {
      "relationshipType": "DEPENDS_ON",
      "relatedSpdxElement": "SPDXRef-Package-C73F0E93BB5784C56E48D3C923A4EE05EFB7687707BEBCBA3ADB4C64496882D6",
      "spdxElementId": "SPDXRef-RootPackage"
    },
    {
      "relationshipType": "DEPENDS_ON",
      "relatedSpdxElement": "SPDXRef-Package-0442CBDB745F42024DDE6CFFE8C78F6B459D8E04E85C4F533C7342F68658B0AB",
      "spdxElementId": "SPDXRef-RootPackage"
    },
    {
      "relationshipType": "DEPENDS_ON",
      "relatedSpdxElement": "SPDXRef-Package-3ED87A63167926B1AD760EEFD8B5F0F80EC92D1B8863633437D0E2B564F3306E",
      "spdxElementId": "SPDXRef-RootPackage"
    },
    {
      "relationshipType": "DEPENDS_ON",
      "relatedSpdxElement": "SPDXRef-Package-93414AC39BB04FFF7097542621AF10D94AA890E8BCB8619AD1C4FADD98FA4E57",
      "spdxElementId": "SPDXRef-RootPackage"
    },
    {
      "relationshipType": "DEPENDS_ON",
      "relatedSpdxElement": "SPDXRef-Package-48B79D5F6FFF98C09DEA83114649014217A3858A32B82AF3FBB9395395A29B7D",
      "spdxElementId": "SPDXRef-RootPackage"
    },
    {
      "relationshipType": "DEPENDS_ON",
      "relatedSpdxElement": "SPDXRef-Package-8446DC2D4DCE972685FA381430FB2C7E28E48031C44055FF8461D0F681A55375",
      "spdxElementId": "SPDXRef-RootPackage"
    },
    {
      "relationshipType": "DEPENDS_ON",
      "relatedSpdxElement": "SPDXRef-Package-B381D93D92547360B20C4C6AE5A15CFDD41E01FCCFAE8A02AFA10BB59F9AB587",
      "spdxElementId": "SPDXRef-RootPackage"
    },
    {
      "relationshipType": "DEPENDS_ON",
      "relatedSpdxElement": "SPDXRef-Package-51B56F5C09F5DB6C5F245A31068CD765872343B3D605D2D03755C248CC4065F8",
      "spdxElementId": "SPDXRef-RootPackage"
    },
    {
      "relationshipType": "DEPENDS_ON",
      "relatedSpdxElement": "SPDXRef-Package-7F7E31A05F83564D6B28A95727EC3CF6C559093084BE16DB4E531A87FEF82825",
      "spdxElementId": "SPDXRef-RootPackage"
    },
    {
      "relationshipType": "DEPENDS_ON",
      "relatedSpdxElement": "SPDXRef-Package-B4121D75D3C0345AE8DC9C682DDA3F17487EFE49ED55F4C9BE31C5132A516695",
      "spdxElementId": "SPDXRef-RootPackage"
    },
    {
      "relationshipType": "DEPENDS_ON",
      "relatedSpdxElement": "SPDXRef-Package-88F9FB27AC142FAC8F1E4FE333AE03873283A2B359795059A076DD0E7C47DA57",
      "spdxElementId": "SPDXRef-RootPackage"
    },
    {
      "relationshipType": "DEPENDS_ON",
      "relatedSpdxElement": "SPDXRef-Package-6F6D35D97F7FAD2044E3A76DD804FAA777D2FCFE708930657ACD9B72D32F637F",
      "spdxElementId": "SPDXRef-RootPackage"
    },
    {
      "relationshipType": "DEPENDS_ON",
      "relatedSpdxElement": "SPDXRef-Package-4DAD0C8B67FB1629FA51ADC4F3B687F7E8956EE6EF103092AED3BF607E477402",
      "spdxElementId": "SPDXRef-RootPackage"
    },
    {
      "relationshipType": "DEPENDS_ON",
      "relatedSpdxElement": "SPDXRef-Package-54752A2D05C113E904C18C1CAAD62C2236CEBD089CC561706EDA4429B4E37FC8",
      "spdxElementId": "SPDXRef-RootPackage"
    },
    {
      "relationshipType": "DEPENDS_ON",
      "relatedSpdxElement": "SPDXRef-Package-7A19B52E8F896DB3BED127884BD6019DD768CE9CCC37946BA4A0EC82B7734049",
      "spdxElementId": "SPDXRef-RootPackage"
    },
    {
      "relationshipType": "DEPENDS_ON",
      "relatedSpdxElement": "SPDXRef-Package-A7E9F216CBCA8DCDD8D155798D23F0C80B0D9F5C988BD006E2155EF2493F69E9",
      "spdxElementId": "SPDXRef-RootPackage"
    },
    {
      "relationshipType": "DEPENDS_ON",
      "relatedSpdxElement": "SPDXRef-Package-E72FE5EB82C2581D4FF7C7136B5703454E56EE69293860B10817C948D14A56E4",
      "spdxElementId": "SPDXRef-RootPackage"
    },
    {
      "relationshipType": "DEPENDS_ON",
      "relatedSpdxElement": "SPDXRef-Package-69CEF2FBDBCDDACA6D718F6DF351C94D394604E3FAC4AF555207490B8C60F265",
      "spdxElementId": "SPDXRef-RootPackage"
    },
    {
      "relationshipType": "DEPENDS_ON",
      "relatedSpdxElement": "SPDXRef-Package-35288EC2044BA02271D28C93E07A11A14C07C3171BC7F82DAD8380D2B88EE690",
      "spdxElementId": "SPDXRef-RootPackage"
    },
    {
      "relationshipType": "DEPENDS_ON",
      "relatedSpdxElement": "SPDXRef-Package-AF8E58564B82E13CA0207F61028BBC26AC45AFED76D355764166AD9564C2197F",
      "spdxElementId": "SPDXRef-RootPackage"
    },
    {
      "relationshipType": "DEPENDS_ON",
      "relatedSpdxElement": "SPDXRef-Package-420C98B9E896762E707F2B9415FE879958DB14C4FD4A11F466D61250CD4356E7",
      "spdxElementId": "SPDXRef-RootPackage"
    },
    {
      "relationshipType": "DEPENDS_ON",
      "relatedSpdxElement": "SPDXRef-Package-212255077A0F752D4251E972D4A69A2AFB9488C0A77DD6F9A66A65C2F78F58F8",
      "spdxElementId": "SPDXRef-RootPackage"
    },
    {
      "relationshipType": "DEPENDS_ON",
      "relatedSpdxElement": "SPDXRef-Package-38B02901A4E91407BF8F822BB760A85D2FC784EF5C91FB60C38FB78206745093",
      "spdxElementId": "SPDXRef-RootPackage"
    },
    {
      "relationshipType": "DEPENDS_ON",
      "relatedSpdxElement": "SPDXRef-Package-EA8DC12E44139D9AC7AD2720FF84433B3E1A0376C441D8D9531FB1942F1DCF57",
      "spdxElementId": "SPDXRef-RootPackage"
    },
    {
      "relationshipType": "DEPENDS_ON",
      "relatedSpdxElement": "SPDXRef-Package-177BFE1A91780FDE779F74A5D45D6B2E30FABB027D42CFFDCF24549F7D394765",
      "spdxElementId": "SPDXRef-RootPackage"
    },
    {
      "relationshipType": "DEPENDS_ON",
      "relatedSpdxElement": "SPDXRef-Package-02BDF6AE45C73E44F28C826A9589F1BA3D6380975FED32E2F332543E21502AFC",
      "spdxElementId": "SPDXRef-RootPackage"
    },
    {
      "relationshipType": "DEPENDS_ON",
      "relatedSpdxElement": "SPDXRef-Package-1B6E1C2ACE25D47A11940D47BD4713978F8102238AE51B61A52A7EF2301D784B",
      "spdxElementId": "SPDXRef-RootPackage"
    },
    {
      "relationshipType": "DEPENDS_ON",
      "relatedSpdxElement": "SPDXRef-Package-2C210F1EC0B25582C773EE8E0EFD3AF282CE522FA5A71968C5790F5F3A921B43",
      "spdxElementId": "SPDXRef-RootPackage"
    },
    {
      "relationshipType": "DEPENDS_ON",
      "relatedSpdxElement": "SPDXRef-Package-36AC1803C583BCDC688F83419CA5509CA3BBB2E134B031F0D59CF5270A5C2F09",
      "spdxElementId": "SPDXRef-RootPackage"
    },
    {
      "relationshipType": "DEPENDS_ON",
      "relatedSpdxElement": "SPDXRef-Package-C789728058FB6A65C5B8CC48C180C7AB809F66D1B9CC529856294FC6FEA74054",
      "spdxElementId": "SPDXRef-RootPackage"
    },
    {
      "relationshipType": "DEPENDS_ON",
      "relatedSpdxElement": "SPDXRef-Package-383A474A54A0F57D652E2CDA0934E113F3DD9B88BB0A8C9142D0BD377D141D32",
      "spdxElementId": "SPDXRef-RootPackage"
    },
    {
      "relationshipType": "DEPENDS_ON",
      "relatedSpdxElement": "SPDXRef-Package-4A5348D7EAD57322A56631311BB791C7B9BB5EC105E5D82CC189CA3EB9A2DA97",
      "spdxElementId": "SPDXRef-RootPackage"
    },
    {
      "relationshipType": "DEPENDS_ON",
      "relatedSpdxElement": "SPDXRef-Package-FA7E8A9DA905CF941B611ED89146A7796BCD28B3E602E4280922ADB1233A053E",
      "spdxElementId": "SPDXRef-RootPackage"
    },
    {
      "relationshipType": "DEPENDS_ON",
      "relatedSpdxElement": "SPDXRef-Package-970D97175DC9F5271B204F15F2803F46CD516DA8DCD46A53C1DA939702ED19FB",
      "spdxElementId": "SPDXRef-RootPackage"
    },
    {
      "relationshipType": "DEPENDS_ON",
      "relatedSpdxElement": "SPDXRef-Package-EDACF26B8AC1A6E7B01AD38693C0939218D98361EAB3F61A94129C51F79B2D18",
      "spdxElementId": "SPDXRef-RootPackage"
    },
    {
      "relationshipType": "DEPENDS_ON",
      "relatedSpdxElement": "SPDXRef-Package-265650581814BCFA8E073975CD6CF38EE37FD498235C00821F158F181BE249AB",
      "spdxElementId": "SPDXRef-RootPackage"
    },
    {
      "relationshipType": "DEPENDS_ON",
      "relatedSpdxElement": "SPDXRef-Package-52135839EA35478FEC48ADC4A6664FC7EE10B96DB2FFFF336D14AF10C6CE7439",
      "spdxElementId": "SPDXRef-RootPackage"
    },
    {
      "relationshipType": "DEPENDS_ON",
      "relatedSpdxElement": "SPDXRef-Package-95F91413D681E88A5A238D8AABB681D58A535AED22A368F757C009930FB6E38F",
      "spdxElementId": "SPDXRef-RootPackage"
    },
    {
      "relationshipType": "DEPENDS_ON",
      "relatedSpdxElement": "SPDXRef-Package-D3216033B89098B889E6A5B95BF6D450EE50C951805B15CE7BC87F828DDD0874",
      "spdxElementId": "SPDXRef-RootPackage"
    },
    {
      "relationshipType": "DEPENDS_ON",
      "relatedSpdxElement": "SPDXRef-Package-5C2D87CEF5257E39ECDCF36FFC7EEFC06F3281D2B8B1DC3EE116F6DEC4E44E21",
      "spdxElementId": "SPDXRef-RootPackage"
    },
    {
      "relationshipType": "DEPENDS_ON",
      "relatedSpdxElement": "SPDXRef-Package-3BF66000678C450DECC5923207ED2D7A836100994D89B829CE6E36757B074D4D",
      "spdxElementId": "SPDXRef-RootPackage"
    },
    {
      "relationshipType": "DEPENDS_ON",
      "relatedSpdxElement": "SPDXRef-Package-601B14C50D96DF5831A949A3F602DE5E9253B66F98A6B3F08CA45862044F2F91",
      "spdxElementId": "SPDXRef-RootPackage"
    },
    {
      "relationshipType": "DEPENDS_ON",
      "relatedSpdxElement": "SPDXRef-Package-13A0F12D6762774B8734415858796EB317A828A8CCAE45B6445B4826231683D0",
      "spdxElementId": "SPDXRef-RootPackage"
    },
    {
      "relationshipType": "DEPENDS_ON",
      "relatedSpdxElement": "SPDXRef-Package-5430C9C15B152CF4564D01458E6A2C601AA0099821F40CCD3CD97EFB8347A6D6",
      "spdxElementId": "SPDXRef-RootPackage"
    },
    {
      "relationshipType": "DEPENDS_ON",
      "relatedSpdxElement": "SPDXRef-Package-E2ABBEF4D19026E4AC818A83BB15586D4ABFE941FB75419716A2C9E4ABFAD230",
      "spdxElementId": "SPDXRef-RootPackage"
    },
    {
      "relationshipType": "DEPENDS_ON",
      "relatedSpdxElement": "SPDXRef-Package-C993CD5D4E60396D8509E6F94C4E05744B913787CE753D67D36BE21B2BE5E55B",
      "spdxElementId": "SPDXRef-RootPackage"
    },
    {
      "relationshipType": "DEPENDS_ON",
      "relatedSpdxElement": "SPDXRef-Package-2074FF2AE4917519B008AA6EBC6A8FA84A55F44FB8845E15093A6C47BB0DE33F",
      "spdxElementId": "SPDXRef-RootPackage"
    },
    {
      "relationshipType": "DEPENDS_ON",
      "relatedSpdxElement": "SPDXRef-Package-770716D2224BBCD4659D448361F9B264F37EFCA10074BE68F41665D0B6608FAB",
      "spdxElementId": "SPDXRef-RootPackage"
    },
    {
      "relationshipType": "DEPENDS_ON",
      "relatedSpdxElement": "SPDXRef-Package-F643431A62DF7430BA4708F4092DF9469A0A79CF1EAA9FC792CDAC6E01FED841",
      "spdxElementId": "SPDXRef-RootPackage"
    },
    {
      "relationshipType": "DEPENDS_ON",
      "relatedSpdxElement": "SPDXRef-Package-FD31658756AFAF5E40E70A899F3D58DF8B433A3836216CA99C9EB523BBB8B82A",
      "spdxElementId": "SPDXRef-RootPackage"
    },
    {
      "relationshipType": "DEPENDS_ON",
      "relatedSpdxElement": "SPDXRef-Package-D8CC961206AD62D4F2E7308905CD165870BA7B3D1FEB82358412CFDB67FA5F33",
      "spdxElementId": "SPDXRef-RootPackage"
    },
    {
      "relationshipType": "DEPENDS_ON",
      "relatedSpdxElement": "SPDXRef-Package-37ED6C4EA8447BD84469A5BA731FCE918BFC31EC55E4565BDE8B09D1542C2637",
      "spdxElementId": "SPDXRef-RootPackage"
    },
    {
      "relationshipType": "DEPENDS_ON",
      "relatedSpdxElement": "SPDXRef-Package-3E43D1393BFB13A294DA3CC1EC1C13F1D02C909DC656C2BCCD7CAD6D0FE83D58",
      "spdxElementId": "SPDXRef-RootPackage"
    },
    {
      "relationshipType": "DEPENDS_ON",
      "relatedSpdxElement": "SPDXRef-Package-6E9661E46BCA09709A7B1AE3FF28BD73BB413D713FC7E81F4FFF417C1BA86B46",
      "spdxElementId": "SPDXRef-RootPackage"
    },
    {
      "relationshipType": "DEPENDS_ON",
      "relatedSpdxElement": "SPDXRef-Package-E64D2F572F330E927B54ADED99252A8365D3EDDAF28A0A35B986E4B6CCC1D4F8",
      "spdxElementId": "SPDXRef-RootPackage"
    },
    {
      "relationshipType": "DEPENDS_ON",
      "relatedSpdxElement": "SPDXRef-Package-0F55AA864794331F872752E9E131DA1A574DBE2C04DB29EAC15CDF0B23DDE19D",
      "spdxElementId": "SPDXRef-RootPackage"
    },
    {
      "relationshipType": "DEPENDS_ON",
      "relatedSpdxElement": "SPDXRef-Package-C5E29D9DF974E203A724C506B3748F05E11C5233AE758A7504C0F0238120DF30",
      "spdxElementId": "SPDXRef-RootPackage"
    },
    {
      "relationshipType": "DEPENDS_ON",
      "relatedSpdxElement": "SPDXRef-Package-59CE747D5453EE558EB7F51BA35C3CE530AADB9FCAAB76B60E84C90C5A363E60",
      "spdxElementId": "SPDXRef-RootPackage"
    },
    {
      "relationshipType": "DEPENDS_ON",
      "relatedSpdxElement": "SPDXRef-Package-7FDEE8E8B947E81084A6A61E4532D4B3AFBB41C9B08E152D811CA14344AFBE01",
      "spdxElementId": "SPDXRef-RootPackage"
    },
    {
      "relationshipType": "DEPENDS_ON",
      "relatedSpdxElement": "SPDXRef-Package-84214E65517E87BEFAC8A979E530703D5E066716352F5947FCF4EBE293AB85CF",
      "spdxElementId": "SPDXRef-RootPackage"
    },
    {
      "relationshipType": "DEPENDS_ON",
      "relatedSpdxElement": "SPDXRef-Package-C6E932756A9242C20A3191625E752B03AF0915B2DC02F3C1DFDB6E9E88F89399",
      "spdxElementId": "SPDXRef-RootPackage"
    },
    {
      "relationshipType": "DEPENDS_ON",
      "relatedSpdxElement": "SPDXRef-Package-18ABA61FD625D3F690D268508DD7171D960D6A34CAD12E94D35EC8504026AC7F",
      "spdxElementId": "SPDXRef-RootPackage"
    },
    {
      "relationshipType": "DEPENDS_ON",
      "relatedSpdxElement": "SPDXRef-Package-65225ED5EB2C24AE796645ED3E67C3BE7C4A1527579A6EB1CC72044B05139627",
      "spdxElementId": "SPDXRef-RootPackage"
    },
    {
      "relationshipType": "DEPENDS_ON",
      "relatedSpdxElement": "SPDXRef-Package-71EB876CFB97EA5AF67046ECA53B3B62ECED15E581E9899721A45E81C904B7B4",
      "spdxElementId": "SPDXRef-RootPackage"
    },
    {
      "relationshipType": "DEPENDS_ON",
      "relatedSpdxElement": "SPDXRef-Package-EC569588B44E6DEF64FD5ABB8107D03E0ABA38AEC9068177157EE6F2464753E1",
      "spdxElementId": "SPDXRef-RootPackage"
    },
    {
      "relationshipType": "DEPENDS_ON",
      "relatedSpdxElement": "SPDXRef-Package-A484D358DF8630A9E8CA5228C8EF114F4B75296BE494FE97A3E5CC25F997E031",
      "spdxElementId": "SPDXRef-RootPackage"
    },
    {
      "relationshipType": "DEPENDS_ON",
      "relatedSpdxElement": "SPDXRef-Package-E41120416AE198ED43DEDF4B7261349A2361E7AFA97EF854D8A3A32C09E324F8",
      "spdxElementId": "SPDXRef-RootPackage"
    }
  ],
  "spdxVersion": "SPDX-2.2",
  "dataLicense": "CC0-1.0",
  "SPDXID": "SPDXRef-DOCUMENT",
  "name": "api v0.30.1",
  "documentNamespace": "https://github.com/Be-Secure/api.git/api/v0.30.1/OqPzU7gKMUWmB2qsu05C1A",
  "creationInfo": {
    "created": "2024-06-03T08:30:20Z",
    "creators": [
      "Organization: wipro",
      "Tool: Microsoft.SBOMTool-1.1.8"
    ]
  },
  "documentDescribes": [
    "SPDXRef-RootPackage"
  ]
}